<?xml version="1.0" encoding="UTF-8"?>

<!-- generated on 2023-04-23 02:36:01 by Eclipse SUMO GUI Version 1.16.0
<configuration xmlns:xsi="http://www.w3.org/2001/XMLSchema-instance" xsi:noNamespaceSchemaLocation="http://sumo.dlr.de/xsd/sumoConfiguration.xsd">

    <input>
        <net-file value="intersection\kinsale.net.xml"/>
        <route-files value="intersection\episode_routes_kinsale.rou.xml"/>
    </input>

    <output>
        <summary-output value="intersection\K-summary-low.xml"/>
        <tripinfo-output value="intersection\K-trip_info-low.xml"/>
    </output>

    <time>
        <begin value="0"/>
    </time>

    <processing>
        <time-to-teleport value="-1"/>
        <waiting-time-memory value="1800"/>
    </processing>

    <report>
        <no-step-log value="true"/>
    </report>

    <traci_server>
        <remote-port value="55288"/>
    </traci_server>

</configuration>
-->

<tripinfos xmlns:xsi="http://www.w3.org/2001/XMLSchema-instance" xsi:noNamespaceSchemaLocation="http://sumo.dlr.de/xsd/tripinfo_file.xsd">
    <tripinfo id="N_E_0" depart="57.00" departLane="E10_0" departPos="5.10" departSpeed="10.00" departDelay="0.00" arrival="133.00" arrivalLane="E23_0" arrivalPos="251.04" arrivalSpeed="14.58" duration="76.00" routeLength="1017.15" waitingTime="0.00" waitingCount="0" stopTime="0.00" timeLoss="5.10" rerouteNo="0" devices="tripinfo_N_E_0" vType="standard_car" speedFactor="1.06" vaporized=""/>
    <tripinfo id="N_E_1" depart="122.00" departLane="E10_1" departPos="5.10" departSpeed="10.00" departDelay="0.00" arrival="207.00" arrivalLane="E23_0" arrivalPos="251.04" arrivalSpeed="12.65" duration="85.00" routeLength="1017.15" waitingTime="0.00" waitingCount="0" stopTime="0.00" timeLoss="5.26" rerouteNo="0" devices="tripinfo_N_E_1" vType="standard_car" speedFactor="0.94" vaporized=""/>
    <tripinfo id="W_E_2" depart="148.00" departLane="E9_2" departPos="5.10" departSpeed="10.00" departDelay="0.00" arrival="233.00" arrivalLane="E22_0" arrivalPos="258.43" arrivalSpeed="13.91" duration="85.00" routeLength="1065.97" waitingTime="0.00" waitingCount="0" stopTime="0.00" timeLoss="7.31" rerouteNo="0" devices="tripinfo_W_E_2" vType="standard_car" speedFactor="1.01" vaporized=""/>
    <tripinfo id="S_W_4" depart="256.00" departLane="E8_2" departPos="5.10" departSpeed="10.00" departDelay="0.00" arrival="373.00" arrivalLane="E21_0" arrivalPos="182.45" arrivalSpeed="14.15" duration="117.00" routeLength="1009.18" waitingTime="29.00" waitingCount="1" stopTime="0.00" timeLoss="44.30" rerouteNo="0" devices="tripinfo_S_W_4" vType="standard_car" speedFactor="1.03" vaporized=""/>
    <tripinfo id="N_W_13" depart="389.00" departLane="E10_0" departPos="5.10" departSpeed="10.00" departDelay="0.00" arrival="462.00" arrivalLane="E22_0" arrivalPos="258.43" arrivalSpeed="15.37" duration="73.00" routeLength="999.87" waitingTime="0.00" waitingCount="0" stopTime="0.00" timeLoss="7.15" rerouteNo="0" devices="tripinfo_N_W_13" vType="standard_car" speedFactor="1.12" vaporized=""/>
    <tripinfo id="E_S_3" depart="169.00" departLane="E11_0" departPos="5.10" departSpeed="10.00" departDelay="0.00" arrival="523.00" arrivalLane="E24_0" arrivalPos="229.28" arrivalSpeed="14.65" duration="354.00" routeLength="984.21" waitingTime="263.00" waitingCount="2" stopTime="0.00" timeLoss="286.48" rerouteNo="0" devices="tripinfo_E_S_3" vType="standard_car" speedFactor="1.08" vaporized=""/>
    <tripinfo id="W_N_15" depart="446.00" departLane="E9_2" departPos="5.10" departSpeed="10.00" departDelay="0.00" arrival="526.00" arrivalLane="E21_0" arrivalPos="182.45" arrivalSpeed="12.50" duration="80.00" routeLength="932.95" waitingTime="0.00" waitingCount="0" stopTime="0.00" timeLoss="5.65" rerouteNo="0" devices="tripinfo_W_N_15" vType="standard_car" speedFactor="0.93" vaporized=""/>
    <tripinfo id="S_N_14" depart="434.00" departLane="E8_1" departPos="5.10" departSpeed="10.00" departDelay="0.00" arrival="539.00" arrivalLane="E23_0" arrivalPos="251.04" arrivalSpeed="13.44" duration="105.00" routeLength="1151.00" waitingTime="2.00" waitingCount="1" stopTime="0.00" timeLoss="18.53" rerouteNo="0" devices="tripinfo_S_N_14" vType="standard_car" speedFactor="0.99" vaporized=""/>
    <tripinfo id="N_E_17" depart="473.00" departLane="E10_1" departPos="5.10" departSpeed="10.00" departDelay="0.00" arrival="558.00" arrivalLane="E23_0" arrivalPos="251.04" arrivalSpeed="12.99" duration="85.00" routeLength="1017.15" waitingTime="0.00" waitingCount="0" stopTime="0.00" timeLoss="5.63" rerouteNo="0" devices="tripinfo_N_E_17" vType="standard_car" speedFactor="0.94" vaporized=""/>
    <tripinfo id="N_E_18" depart="475.00" departLane="E10_1" departPos="5.10" departSpeed="10.00" departDelay="1.00" arrival="563.00" arrivalLane="E23_0" arrivalPos="251.04" arrivalSpeed="12.63" duration="88.00" routeLength="1017.15" waitingTime="0.00" waitingCount="0" stopTime="0.00" timeLoss="8.17" rerouteNo="0" devices="tripinfo_N_E_18" vType="standard_car" speedFactor="0.94" vaporized=""/>
    <tripinfo id="S_E_22" depart="494.00" departLane="E8_0" departPos="5.10" departSpeed="10.00" departDelay="0.00" arrival="566.00" arrivalLane="E24_0" arrivalPos="229.28" arrivalSpeed="13.54" duration="72.00" routeLength="905.97" waitingTime="0.00" waitingCount="0" stopTime="0.00" timeLoss="3.78" rerouteNo="0" devices="tripinfo_S_E_22" vType="standard_car" speedFactor="0.97" vaporized=""/>
    <tripinfo id="E_W_6" depart="306.00" departLane="E11_1" departPos="5.10" departSpeed="10.00" departDelay="0.00" arrival="581.00" arrivalLane="E21_0" arrivalPos="182.45" arrivalSpeed="14.07" duration="275.00" routeLength="1078.04" waitingTime="162.00" waitingCount="2" stopTime="0.00" timeLoss="198.14" rerouteNo="0" devices="tripinfo_E_W_6" vType="standard_car" speedFactor="1.05" vaporized=""/>
    <tripinfo id="E_S_5" depart="304.00" departLane="E11_1" departPos="5.10" departSpeed="10.00" departDelay="0.00" arrival="583.00" arrivalLane="E24_0" arrivalPos="229.28" arrivalSpeed="11.26" duration="279.00" routeLength="984.21" waitingTime="170.00" waitingCount="2" stopTime="0.00" timeLoss="191.57" rerouteNo="0" devices="tripinfo_E_S_5" vType="standard_car" speedFactor="0.83" vaporized=""/>
    <tripinfo id="N_S_16" depart="471.00" departLane="E10_0" departPos="5.10" departSpeed="10.00" departDelay="0.00" arrival="585.00" arrivalLane="E24_0" arrivalPos="229.28" arrivalSpeed="12.07" duration="114.00" routeLength="1051.83" waitingTime="8.00" waitingCount="1" stopTime="0.00" timeLoss="24.68" rerouteNo="0" devices="tripinfo_N_S_16" vType="standard_car" speedFactor="0.88" vaporized=""/>
    <tripinfo id="N_S_19" depart="481.00" departLane="E10_0" departPos="5.10" departSpeed="10.00" departDelay="0.00" arrival="587.00" arrivalLane="E24_0" arrivalPos="229.28" arrivalSpeed="14.10" duration="106.00" routeLength="1051.83" waitingTime="1.00" waitingCount="1" stopTime="0.00" timeLoss="38.33" rerouteNo="0" devices="tripinfo_N_S_19" vType="standard_car" speedFactor="1.16" vaporized=""/>
    <tripinfo id="S_W_20" depart="482.00" departLane="E8_0" departPos="5.10" departSpeed="10.00" departDelay="0.00" arrival="587.00" arrivalLane="E21_1" arrivalPos="182.45" arrivalSpeed="13.89" duration="105.00" routeLength="1006.25" waitingTime="10.00" waitingCount="1" stopTime="0.00" timeLoss="31.48" rerouteNo="0" devices="tripinfo_S_W_20" vType="standard_car" speedFactor="1.02" vaporized=""/>
    <tripinfo id="W_E_10" depart="363.00" departLane="E9_0" departPos="5.10" departSpeed="10.00" departDelay="0.00" arrival="591.00" arrivalLane="E22_0" arrivalPos="258.43" arrivalSpeed="14.73" duration="228.00" routeLength="1065.97" waitingTime="130.00" waitingCount="2" stopTime="0.00" timeLoss="155.54" rerouteNo="0" devices="tripinfo_W_E_10" vType="standard_car" speedFactor="1.09" vaporized=""/>
    <tripinfo id="E_S_8" depart="318.00" departLane="E11_2" departPos="5.10" departSpeed="10.00" departDelay="0.00" arrival="594.00" arrivalLane="E24_0" arrivalPos="229.28" arrivalSpeed="13.01" duration="276.00" routeLength="984.21" waitingTime="165.00" waitingCount="5" stopTime="0.00" timeLoss="198.40" rerouteNo="0" devices="tripinfo_E_S_8" vType="standard_car" speedFactor="0.94" vaporized=""/>
    <tripinfo id="W_S_12" depart="371.00" departLane="E9_2" departPos="5.10" departSpeed="10.00" departDelay="0.00" arrival="595.00" arrivalLane="E23_0" arrivalPos="251.04" arrivalSpeed="14.42" duration="224.00" routeLength="1083.25" waitingTime="121.00" waitingCount="2" stopTime="0.00" timeLoss="147.59" rerouteNo="0" devices="tripinfo_W_S_12" vType="standard_car" speedFactor="1.05" vaporized=""/>
    <tripinfo id="W_E_11" depart="368.00" departLane="E9_0" departPos="5.10" departSpeed="10.00" departDelay="0.00" arrival="596.00" arrivalLane="E22_0" arrivalPos="258.43" arrivalSpeed="14.03" duration="228.00" routeLength="1065.97" waitingTime="123.00" waitingCount="2" stopTime="0.00" timeLoss="151.13" rerouteNo="0" devices="tripinfo_W_E_11" vType="standard_car" speedFactor="1.03" vaporized=""/>
    <tripinfo id="S_E_25" depart="505.00" departLane="E8_1" departPos="5.10" departSpeed="10.00" departDelay="0.00" arrival="597.00" arrivalLane="E24_0" arrivalPos="229.28" arrivalSpeed="11.74" duration="92.00" routeLength="905.97" waitingTime="5.00" waitingCount="1" stopTime="0.00" timeLoss="15.62" rerouteNo="0" devices="tripinfo_S_E_25" vType="standard_car" speedFactor="0.87" vaporized=""/>
    <tripinfo id="N_W_28" depart="521.00" departLane="E10_0" departPos="5.10" departSpeed="10.00" departDelay="0.00" arrival="606.00" arrivalLane="E22_0" arrivalPos="258.43" arrivalSpeed="15.50" duration="85.00" routeLength="999.87" waitingTime="2.00" waitingCount="1" stopTime="0.00" timeLoss="19.97" rerouteNo="0" devices="tripinfo_N_W_28" vType="standard_car" speedFactor="1.13" vaporized=""/>
    <tripinfo id="N_E_23" depart="500.00" departLane="E10_0" departPos="5.10" departSpeed="10.00" departDelay="0.00" arrival="608.00" arrivalLane="E23_0" arrivalPos="251.04" arrivalSpeed="11.97" duration="108.00" routeLength="1017.15" waitingTime="11.00" waitingCount="1" stopTime="0.00" timeLoss="24.01" rerouteNo="0" devices="tripinfo_N_E_23" vType="standard_car" speedFactor="0.89" vaporized=""/>
    <tripinfo id="N_E_30" depart="556.00" departLane="E10_0" departPos="5.10" departSpeed="10.00" departDelay="0.00" arrival="627.00" arrivalLane="E23_0" arrivalPos="251.04" arrivalSpeed="16.03" duration="71.00" routeLength="1017.15" waitingTime="0.00" waitingCount="0" stopTime="0.00" timeLoss="7.20" rerouteNo="0" devices="tripinfo_N_E_30" vType="standard_car" speedFactor="1.18" vaporized=""/>
    <tripinfo id="S_W_26" depart="508.00" departLane="E8_2" departPos="5.10" departSpeed="10.00" departDelay="0.00" arrival="661.00" arrivalLane="E21_1" arrivalPos="182.45" arrivalSpeed="12.31" duration="153.00" routeLength="1009.18" waitingTime="48.00" waitingCount="2" stopTime="0.00" timeLoss="70.78" rerouteNo="0" devices="tripinfo_S_W_26" vType="standard_car" speedFactor="0.92" vaporized=""/>
    <tripinfo id="E_W_7" depart="308.00" departLane="E11_1" departPos="5.10" departSpeed="10.00" departDelay="2.00" arrival="662.00" arrivalLane="E21_0" arrivalPos="182.45" arrivalSpeed="11.96" duration="354.00" routeLength="1078.04" waitingTime="218.00" waitingCount="3" stopTime="0.00" timeLoss="261.18" rerouteNo="0" devices="tripinfo_E_W_7" vType="standard_car" speedFactor="0.89" vaporized=""/>
    <tripinfo id="E_S_24" depart="502.00" departLane="E11_0" departPos="5.10" departSpeed="10.00" departDelay="0.00" arrival="663.00" arrivalLane="E24_0" arrivalPos="229.28" arrivalSpeed="11.44" duration="161.00" routeLength="984.21" waitingTime="59.00" waitingCount="1" stopTime="0.00" timeLoss="72.39" rerouteNo="0" devices="tripinfo_E_S_24" vType="standard_car" speedFactor="0.83" vaporized=""/>
    <tripinfo id="N_S_21" depart="491.00" departLane="E10_1" departPos="5.10" departSpeed="10.00" departDelay="0.00" arrival="666.00" arrivalLane="E24_0" arrivalPos="229.28" arrivalSpeed="13.60" duration="175.00" routeLength="1051.83" waitingTime="67.00" waitingCount="2" stopTime="0.00" timeLoss="97.68" rerouteNo="0" devices="tripinfo_N_S_21" vType="standard_car" speedFactor="1.01" vaporized=""/>
    <tripinfo id="N_S_29" depart="536.00" departLane="E10_1" departPos="5.10" departSpeed="10.00" departDelay="0.00" arrival="669.00" arrivalLane="E24_0" arrivalPos="229.28" arrivalSpeed="12.77" duration="133.00" routeLength="1051.83" waitingTime="24.00" waitingCount="2" stopTime="0.00" timeLoss="48.85" rerouteNo="0" devices="tripinfo_N_S_29" vType="standard_car" speedFactor="0.93" vaporized=""/>
    <tripinfo id="W_E_27" depart="510.00" departLane="E9_1" departPos="5.10" departSpeed="10.00" departDelay="0.00" arrival="671.00" arrivalLane="E22_0" arrivalPos="258.43" arrivalSpeed="12.82" duration="161.00" routeLength="1065.97" waitingTime="63.00" waitingCount="1" stopTime="0.00" timeLoss="78.35" rerouteNo="0" devices="tripinfo_W_E_27" vType="standard_car" speedFactor="0.95" vaporized=""/>
    <tripinfo id="S_E_36" depart="599.00" departLane="E8_1" departPos="5.10" departSpeed="10.00" departDelay="0.00" arrival="671.00" arrivalLane="E24_0" arrivalPos="229.28" arrivalSpeed="13.49" duration="72.00" routeLength="905.97" waitingTime="0.00" waitingCount="0" stopTime="0.00" timeLoss="3.67" rerouteNo="0" devices="tripinfo_S_E_36" vType="standard_car" speedFactor="0.97" vaporized=""/>
    <tripinfo id="E_W_9" depart="321.00" departLane="E11_0" departPos="5.10" departSpeed="10.00" departDelay="0.00" arrival="689.00" arrivalLane="E21_0" arrivalPos="182.45" arrivalSpeed="11.58" duration="368.00" routeLength="1078.04" waitingTime="232.00" waitingCount="4" stopTime="0.00" timeLoss="273.92" rerouteNo="0" devices="tripinfo_E_W_9" vType="standard_car" speedFactor="0.86" vaporized=""/>
    <tripinfo id="N_E_33" depart="593.00" departLane="E10_1" departPos="5.10" departSpeed="10.00" departDelay="0.00" arrival="701.00" arrivalLane="E23_0" arrivalPos="251.04" arrivalSpeed="15.87" duration="108.00" routeLength="1017.15" waitingTime="17.00" waitingCount="2" stopTime="0.00" timeLoss="44.17" rerouteNo="0" devices="tripinfo_N_E_33" vType="standard_car" speedFactor="1.17" vaporized=""/>
    <tripinfo id="W_E_32" depart="588.00" departLane="E9_2" departPos="5.10" departSpeed="10.00" departDelay="0.00" arrival="708.00" arrivalLane="E22_0" arrivalPos="258.43" arrivalSpeed="13.50" duration="120.00" routeLength="1065.97" waitingTime="13.00" waitingCount="2" stopTime="0.00" timeLoss="41.48" rerouteNo="0" devices="tripinfo_W_E_32" vType="standard_car" speedFactor="1.01" vaporized=""/>
    <tripinfo id="N_E_37" depart="600.00" departLane="E10_1" departPos="5.10" departSpeed="10.00" departDelay="0.00" arrival="711.00" arrivalLane="E23_0" arrivalPos="251.04" arrivalSpeed="15.96" duration="111.00" routeLength="1017.15" waitingTime="9.00" waitingCount="3" stopTime="0.00" timeLoss="47.67" rerouteNo="0" devices="tripinfo_N_E_37" vType="standard_car" speedFactor="1.18" vaporized=""/>
    <tripinfo id="S_N_35" depart="597.00" departLane="E8_2" departPos="5.10" departSpeed="10.00" departDelay="0.00" arrival="716.00" arrivalLane="E23_0" arrivalPos="251.04" arrivalSpeed="13.94" duration="119.00" routeLength="1151.00" waitingTime="2.00" waitingCount="1" stopTime="0.00" timeLoss="34.65" rerouteNo="0" devices="tripinfo_S_N_35" vType="standard_car" speedFactor="1.02" vaporized=""/>
    <tripinfo id="N_W_41" depart="632.00" departLane="E10_0" departPos="5.10" departSpeed="10.00" departDelay="0.00" arrival="717.00" arrivalLane="E22_0" arrivalPos="258.43" arrivalSpeed="12.85" duration="85.00" routeLength="999.87" waitingTime="0.00" waitingCount="0" stopTime="0.00" timeLoss="8.60" rerouteNo="0" devices="tripinfo_N_W_41" vType="standard_car" speedFactor="0.96" vaporized=""/>
    <tripinfo id="W_E_31" depart="564.00" departLane="E9_2" departPos="5.10" departSpeed="10.00" departDelay="0.00" arrival="719.00" arrivalLane="E22_0" arrivalPos="258.43" arrivalSpeed="15.62" duration="155.00" routeLength="1065.97" waitingTime="36.00" waitingCount="4" stopTime="0.00" timeLoss="86.71" rerouteNo="0" devices="tripinfo_W_E_31" vType="standard_car" speedFactor="1.15" vaporized=""/>
    <tripinfo id="E_N_40" depart="629.00" departLane="E11_1" departPos="5.10" departSpeed="10.00" departDelay="0.00" arrival="755.00" arrivalLane="E22_0" arrivalPos="258.43" arrivalSpeed="13.93" duration="126.00" routeLength="924.43" waitingTime="48.00" waitingCount="1" stopTime="0.00" timeLoss="60.70" rerouteNo="0" devices="tripinfo_E_N_40" vType="standard_car" speedFactor="1.03" vaporized=""/>
    <tripinfo id="N_W_47" depart="666.00" departLane="E10_0" departPos="5.10" departSpeed="10.00" departDelay="0.00" arrival="775.00" arrivalLane="E22_0" arrivalPos="258.43" arrivalSpeed="12.51" duration="109.00" routeLength="999.87" waitingTime="11.00" waitingCount="1" stopTime="0.00" timeLoss="26.75" rerouteNo="0" devices="tripinfo_N_W_47" vType="standard_car" speedFactor="0.90" vaporized=""/>
    <tripinfo id="N_W_48" depart="668.00" departLane="E10_1" departPos="5.10" departSpeed="10.00" departDelay="0.00" arrival="777.00" arrivalLane="E22_0" arrivalPos="258.43" arrivalSpeed="12.14" duration="109.00" routeLength="999.87" waitingTime="5.00" waitingCount="2" stopTime="0.00" timeLoss="24.49" rerouteNo="0" devices="tripinfo_N_W_48" vType="standard_car" speedFactor="0.88" vaporized=""/>
    <tripinfo id="W_S_34" depart="597.00" departLane="E9_1" departPos="5.10" departSpeed="10.00" departDelay="0.00" arrival="781.00" arrivalLane="E23_0" arrivalPos="251.04" arrivalSpeed="13.62" duration="184.00" routeLength="1083.25" waitingTime="67.00" waitingCount="3" stopTime="0.00" timeLoss="103.93" rerouteNo="0" devices="tripinfo_W_S_34" vType="standard_car" speedFactor="0.99" vaporized=""/>
    <tripinfo id="E_S_44" depart="647.00" departLane="E11_1" departPos="5.10" departSpeed="10.00" departDelay="0.00" arrival="781.00" arrivalLane="E24_0" arrivalPos="229.28" arrivalSpeed="14.34" duration="134.00" routeLength="984.21" waitingTime="43.00" waitingCount="2" stopTime="0.00" timeLoss="64.28" rerouteNo="0" devices="tripinfo_E_S_44" vType="standard_car" speedFactor="1.04" vaporized=""/>
    <tripinfo id="E_S_46" depart="663.00" departLane="E11_1" departPos="5.10" departSpeed="10.00" departDelay="0.00" arrival="788.00" arrivalLane="E24_0" arrivalPos="229.28" arrivalSpeed="13.70" duration="125.00" routeLength="984.21" waitingTime="26.00" waitingCount="3" stopTime="0.00" timeLoss="51.19" rerouteNo="0" devices="tripinfo_E_S_46" vType="standard_car" speedFactor="1.00" vaporized=""/>
    <tripinfo id="E_W_39" depart="613.00" departLane="E11_1" departPos="5.10" departSpeed="10.00" departDelay="0.00" arrival="790.00" arrivalLane="E21_0" arrivalPos="182.45" arrivalSpeed="12.27" duration="177.00" routeLength="1081.57" waitingTime="52.00" waitingCount="2" stopTime="0.00" timeLoss="86.54" rerouteNo="0" devices="tripinfo_E_W_39" vType="standard_car" speedFactor="0.90" vaporized=""/>
    <tripinfo id="E_S_45" depart="652.00" departLane="E11_1" departPos="5.10" departSpeed="10.00" departDelay="0.00" arrival="790.00" arrivalLane="E24_0" arrivalPos="229.28" arrivalSpeed="14.88" duration="138.00" routeLength="980.30" waitingTime="37.00" waitingCount="3" stopTime="0.00" timeLoss="70.53" rerouteNo="0" devices="tripinfo_E_S_45" vType="standard_car" speedFactor="1.09" vaporized=""/>
    <tripinfo id="E_W_38" depart="611.00" departLane="E11_2" departPos="5.10" departSpeed="10.00" departDelay="0.00" arrival="793.00" arrivalLane="E21_1" arrivalPos="182.45" arrivalSpeed="15.11" duration="182.00" routeLength="1081.57" waitingTime="56.00" waitingCount="4" stopTime="0.00" timeLoss="107.12" rerouteNo="0" devices="tripinfo_E_W_38" vType="standard_car" speedFactor="1.10" vaporized=""/>
    <tripinfo id="W_N_53" depart="699.00" departLane="E9_2" departPos="5.10" departSpeed="10.00" departDelay="0.00" arrival="799.00" arrivalLane="E21_1" arrivalPos="182.45" arrivalSpeed="15.04" duration="100.00" routeLength="941.43" waitingTime="9.00" waitingCount="1" stopTime="0.00" timeLoss="36.06" rerouteNo="0" devices="tripinfo_W_N_53" vType="standard_car" speedFactor="1.10" vaporized=""/>
    <tripinfo id="W_N_55" depart="702.00" departLane="E9_2" departPos="5.10" departSpeed="10.00" departDelay="0.00" arrival="801.00" arrivalLane="E21_0" arrivalPos="182.45" arrivalSpeed="13.82" duration="99.00" routeLength="935.42" waitingTime="3.00" waitingCount="1" stopTime="0.00" timeLoss="29.79" rerouteNo="0" devices="tripinfo_W_N_55" vType="standard_car" speedFactor="1.00" vaporized=""/>
    <tripinfo id="S_N_42" depart="638.00" departLane="E8_1" departPos="5.10" departSpeed="10.00" departDelay="0.00" arrival="808.00" arrivalLane="E23_0" arrivalPos="251.04" arrivalSpeed="14.87" duration="170.00" routeLength="1151.00" waitingTime="56.00" waitingCount="3" stopTime="0.00" timeLoss="91.22" rerouteNo="0" devices="tripinfo_S_N_42" vType="standard_car" speedFactor="1.09" vaporized=""/>
    <tripinfo id="W_S_50" depart="680.00" departLane="E9_0" departPos="5.10" departSpeed="10.00" departDelay="0.00" arrival="815.00" arrivalLane="E23_0" arrivalPos="251.04" arrivalSpeed="11.48" duration="135.00" routeLength="1083.25" waitingTime="20.00" waitingCount="2" stopTime="0.00" timeLoss="42.55" rerouteNo="0" devices="tripinfo_W_S_50" vType="standard_car" speedFactor="0.85" vaporized=""/>
    <tripinfo id="W_S_58" depart="716.00" departLane="E9_2" departPos="5.10" departSpeed="10.00" departDelay="0.00" arrival="817.00" arrivalLane="E23_0" arrivalPos="251.04" arrivalSpeed="14.03" duration="101.00" routeLength="1083.25" waitingTime="6.00" waitingCount="1" stopTime="0.00" timeLoss="23.29" rerouteNo="0" devices="tripinfo_W_S_58" vType="standard_car" speedFactor="1.02" vaporized=""/>
    <tripinfo id="S_N_43" depart="644.00" departLane="E8_0" departPos="5.10" departSpeed="10.00" departDelay="0.00" arrival="822.00" arrivalLane="E23_0" arrivalPos="251.04" arrivalSpeed="14.09" duration="178.00" routeLength="1151.00" waitingTime="37.00" waitingCount="4" stopTime="0.00" timeLoss="94.13" rerouteNo="0" devices="tripinfo_S_N_43" vType="standard_car" speedFactor="1.04" vaporized=""/>
    <tripinfo id="N_E_62" depart="737.00" departLane="E10_1" departPos="5.10" departSpeed="10.00" departDelay="0.00" arrival="825.00" arrivalLane="E23_0" arrivalPos="251.04" arrivalSpeed="13.90" duration="88.00" routeLength="1017.15" waitingTime="0.00" waitingCount="0" stopTime="0.00" timeLoss="14.59" rerouteNo="0" devices="tripinfo_N_E_62" vType="standard_car" speedFactor="1.02" vaporized=""/>
    <tripinfo id="N_W_59" depart="720.00" departLane="E10_1" departPos="5.10" departSpeed="10.00" departDelay="0.00" arrival="826.00" arrivalLane="E22_0" arrivalPos="258.43" arrivalSpeed="13.15" duration="106.00" routeLength="999.87" waitingTime="7.00" waitingCount="1" stopTime="0.00" timeLoss="29.45" rerouteNo="0" devices="tripinfo_N_W_59" vType="standard_car" speedFactor="0.97" vaporized=""/>
    <tripinfo id="W_S_51" depart="682.00" departLane="E9_2" departPos="5.10" departSpeed="10.00" departDelay="0.00" arrival="832.00" arrivalLane="E23_0" arrivalPos="251.04" arrivalSpeed="16.17" duration="150.00" routeLength="1083.25" waitingTime="19.00" waitingCount="5" stopTime="0.00" timeLoss="81.44" rerouteNo="0" devices="tripinfo_W_S_51" vType="standard_car" speedFactor="1.17" vaporized=""/>
    <tripinfo id="N_E_68" depart="754.00" departLane="E10_0" departPos="5.10" departSpeed="10.00" departDelay="1.00" arrival="834.00" arrivalLane="E23_1" arrivalPos="251.04" arrivalSpeed="14.04" duration="80.00" routeLength="1017.15" waitingTime="0.00" waitingCount="0" stopTime="0.00" timeLoss="7.80" rerouteNo="0" devices="tripinfo_N_E_68" vType="standard_car" speedFactor="1.04" vaporized=""/>
    <tripinfo id="N_W_65" depart="745.00" departLane="E10_1" departPos="5.10" departSpeed="10.00" departDelay="0.00" arrival="835.00" arrivalLane="E22_0" arrivalPos="258.43" arrivalSpeed="12.01" duration="90.00" routeLength="999.87" waitingTime="0.00" waitingCount="0" stopTime="0.00" timeLoss="6.21" rerouteNo="0" devices="tripinfo_N_W_65" vType="standard_car" speedFactor="0.88" vaporized=""/>
    <tripinfo id="E_W_52" depart="693.00" departLane="E11_2" departPos="5.10" departSpeed="10.00" departDelay="0.00" arrival="843.00" arrivalLane="E21_0" arrivalPos="182.45" arrivalSpeed="13.65" duration="150.00" routeLength="1078.04" waitingTime="30.00" waitingCount="3" stopTime="0.00" timeLoss="69.61" rerouteNo="0" devices="tripinfo_E_W_52" vType="standard_car" speedFactor="1.02" vaporized=""/>
    <tripinfo id="E_W_54" depart="701.00" departLane="E11_1" departPos="5.10" departSpeed="10.00" departDelay="0.00" arrival="843.00" arrivalLane="E21_1" arrivalPos="182.45" arrivalSpeed="13.61" duration="142.00" routeLength="1081.57" waitingTime="23.00" waitingCount="2" stopTime="0.00" timeLoss="59.70" rerouteNo="0" devices="tripinfo_E_W_54" vType="standard_car" speedFactor="1.00" vaporized=""/>
    <tripinfo id="N_S_49" depart="670.00" departLane="E10_0" departPos="5.10" departSpeed="10.00" departDelay="1.00" arrival="845.00" arrivalLane="E24_0" arrivalPos="229.28" arrivalSpeed="11.80" duration="175.00" routeLength="1051.83" waitingTime="32.00" waitingCount="4" stopTime="0.00" timeLoss="81.86" rerouteNo="0" devices="tripinfo_N_S_49" vType="standard_car" speedFactor="0.85" vaporized=""/>
    <tripinfo id="E_W_57" depart="706.00" departLane="E11_2" departPos="5.10" departSpeed="10.00" departDelay="0.00" arrival="846.00" arrivalLane="E21_1" arrivalPos="182.45" arrivalSpeed="15.46" duration="140.00" routeLength="1081.57" waitingTime="19.00" waitingCount="2" stopTime="0.00" timeLoss="69.14" rerouteNo="0" devices="tripinfo_E_W_57" vType="standard_car" speedFactor="1.14" vaporized=""/>
    <tripinfo id="E_S_60" depart="727.00" departLane="E11_2" departPos="5.10" departSpeed="10.00" departDelay="0.00" arrival="848.00" arrivalLane="E24_0" arrivalPos="229.28" arrivalSpeed="15.03" duration="121.00" routeLength="980.30" waitingTime="33.00" waitingCount="2" stopTime="0.00" timeLoss="53.47" rerouteNo="0" devices="tripinfo_E_S_60" vType="standard_car" speedFactor="1.08" vaporized=""/>
    <tripinfo id="W_S_61" depart="733.00" departLane="E9_0" departPos="5.10" departSpeed="10.00" departDelay="0.00" arrival="850.00" arrivalLane="E23_0" arrivalPos="251.04" arrivalSpeed="15.48" duration="117.00" routeLength="1083.25" waitingTime="30.00" waitingCount="1" stopTime="0.00" timeLoss="45.96" rerouteNo="0" devices="tripinfo_W_S_61" vType="standard_car" speedFactor="1.12" vaporized=""/>
    <tripinfo id="N_W_66" depart="753.00" departLane="E10_1" departPos="5.10" departSpeed="10.00" departDelay="0.00" arrival="858.00" arrivalLane="E22_0" arrivalPos="258.43" arrivalSpeed="12.57" duration="105.00" routeLength="999.87" waitingTime="10.00" waitingCount="1" stopTime="0.00" timeLoss="23.30" rerouteNo="0" devices="tripinfo_N_W_66" vType="standard_car" speedFactor="0.91" vaporized=""/>
    <tripinfo id="S_N_56" depart="705.00" departLane="E8_1" departPos="5.10" departSpeed="10.00" departDelay="0.00" arrival="861.00" arrivalLane="E23_0" arrivalPos="251.04" arrivalSpeed="12.25" duration="156.00" routeLength="1151.00" waitingTime="31.00" waitingCount="2" stopTime="0.00" timeLoss="60.33" rerouteNo="0" devices="tripinfo_S_N_56" vType="standard_car" speedFactor="0.90" vaporized=""/>
    <tripinfo id="N_E_79" depart="786.00" departLane="E10_1" departPos="5.10" departSpeed="10.00" departDelay="0.00" arrival="868.00" arrivalLane="E23_0" arrivalPos="251.04" arrivalSpeed="14.77" duration="82.00" routeLength="1017.15" waitingTime="0.00" waitingCount="0" stopTime="0.00" timeLoss="12.90" rerouteNo="0" devices="tripinfo_N_E_79" vType="standard_car" speedFactor="1.09" vaporized=""/>
    <tripinfo id="S_W_76" depart="782.00" departLane="E8_1" departPos="5.10" departSpeed="10.00" departDelay="0.00" arrival="938.00" arrivalLane="E21_0" arrivalPos="182.45" arrivalSpeed="14.21" duration="156.00" routeLength="1002.72" waitingTime="56.00" waitingCount="1" stopTime="0.00" timeLoss="83.63" rerouteNo="0" devices="tripinfo_S_W_76" vType="standard_car" speedFactor="1.03" vaporized=""/>
    <tripinfo id="N_S_77" depart="783.00" departLane="E10_0" departPos="5.10" departSpeed="10.00" departDelay="0.00" arrival="939.00" arrivalLane="E24_0" arrivalPos="229.28" arrivalSpeed="13.47" duration="156.00" routeLength="1051.83" waitingTime="61.00" waitingCount="1" stopTime="0.00" timeLoss="75.89" rerouteNo="0" devices="tripinfo_N_S_77" vType="standard_car" speedFactor="0.98" vaporized=""/>
    <tripinfo id="E_N_87" depart="817.00" departLane="E11_0" departPos="5.10" departSpeed="10.00" departDelay="0.00" arrival="940.00" arrivalLane="E22_0" arrivalPos="258.43" arrivalSpeed="14.48" duration="123.00" routeLength="924.43" waitingTime="44.00" waitingCount="1" stopTime="0.00" timeLoss="57.41" rerouteNo="0" devices="tripinfo_E_N_87" vType="standard_car" speedFactor="1.04" vaporized=""/>
    <tripinfo id="S_W_64" depart="743.00" departLane="E8_2" departPos="5.10" departSpeed="10.00" departDelay="0.00" arrival="942.00" arrivalLane="E21_1" arrivalPos="182.45" arrivalSpeed="12.60" duration="199.00" routeLength="1009.18" waitingTime="93.00" waitingCount="3" stopTime="0.00" timeLoss="119.17" rerouteNo="0" devices="tripinfo_S_W_64" vType="standard_car" speedFactor="0.94" vaporized=""/>
    <tripinfo id="N_S_90" depart="828.00" departLane="E10_0" departPos="5.10" departSpeed="10.00" departDelay="0.00" arrival="944.00" arrivalLane="E24_0" arrivalPos="229.28" arrivalSpeed="14.05" duration="116.00" routeLength="1051.83" waitingTime="16.00" waitingCount="1" stopTime="0.00" timeLoss="38.62" rerouteNo="0" devices="tripinfo_N_S_90" vType="standard_car" speedFactor="1.02" vaporized=""/>
    <tripinfo id="S_W_84" depart="809.00" departLane="E8_0" departPos="5.10" departSpeed="10.00" departDelay="0.00" arrival="949.00" arrivalLane="E21_0" arrivalPos="182.45" arrivalSpeed="15.55" duration="140.00" routeLength="1006.25" waitingTime="47.00" waitingCount="1" stopTime="0.00" timeLoss="75.09" rerouteNo="0" devices="tripinfo_S_W_84" vType="standard_car" speedFactor="1.15" vaporized=""/>
    <tripinfo id="N_S_92" depart="835.00" departLane="E10_1" departPos="5.10" departSpeed="10.00" departDelay="0.00" arrival="952.00" arrivalLane="E24_0" arrivalPos="229.28" arrivalSpeed="11.36" duration="117.00" routeLength="1051.83" waitingTime="1.00" waitingCount="1" stopTime="0.00" timeLoss="21.97" rerouteNo="0" devices="tripinfo_N_S_92" vType="standard_car" speedFactor="0.83" vaporized=""/>
    <tripinfo id="E_S_81" depart="794.00" departLane="E11_1" departPos="5.10" departSpeed="10.00" departDelay="0.00" arrival="953.00" arrivalLane="E24_0" arrivalPos="229.28" arrivalSpeed="11.97" duration="159.00" routeLength="984.21" waitingTime="66.00" waitingCount="1" stopTime="0.00" timeLoss="86.35" rerouteNo="0" devices="tripinfo_E_S_81" vType="standard_car" speedFactor="1.00" vaporized=""/>
    <tripinfo id="S_W_70" depart="764.00" departLane="E8_0" departPos="5.10" departSpeed="10.00" departDelay="0.00" arrival="954.00" arrivalLane="E21_1" arrivalPos="182.45" arrivalSpeed="13.93" duration="190.00" routeLength="1009.18" waitingTime="78.00" waitingCount="3" stopTime="0.00" timeLoss="116.65" rerouteNo="0" devices="tripinfo_S_W_70" vType="standard_car" speedFactor="1.02" vaporized=""/>
    <tripinfo id="S_W_75" depart="780.00" departLane="E8_2" departPos="5.10" departSpeed="10.00" departDelay="0.00" arrival="959.00" arrivalLane="E21_1" arrivalPos="182.45" arrivalSpeed="13.38" duration="179.00" routeLength="1009.18" waitingTime="66.00" waitingCount="1" stopTime="0.00" timeLoss="102.61" rerouteNo="0" devices="tripinfo_S_W_75" vType="standard_car" speedFactor="0.98" vaporized=""/>
    <tripinfo id="N_S_88" depart="819.00" departLane="E10_1" departPos="5.10" departSpeed="10.00" departDelay="0.00" arrival="959.00" arrivalLane="E24_0" arrivalPos="229.28" arrivalSpeed="13.61" duration="140.00" routeLength="1051.83" waitingTime="30.00" waitingCount="2" stopTime="0.00" timeLoss="62.31" rerouteNo="0" devices="tripinfo_N_S_88" vType="standard_car" speedFactor="1.01" vaporized=""/>
    <tripinfo id="W_E_72" depart="770.00" departLane="E9_1" departPos="5.10" departSpeed="10.00" departDelay="0.00" arrival="962.00" arrivalLane="E22_0" arrivalPos="258.43" arrivalSpeed="12.62" duration="192.00" routeLength="1065.97" waitingTime="82.00" waitingCount="1" stopTime="0.00" timeLoss="107.57" rerouteNo="0" devices="tripinfo_W_E_72" vType="standard_car" speedFactor="0.94" vaporized=""/>
    <tripinfo id="W_E_63" depart="742.00" departLane="E9_2" departPos="5.10" departSpeed="10.00" departDelay="0.00" arrival="965.00" arrivalLane="E22_0" arrivalPos="258.43" arrivalSpeed="13.42" duration="223.00" routeLength="1065.97" waitingTime="107.00" waitingCount="4" stopTime="0.00" timeLoss="142.53" rerouteNo="0" devices="tripinfo_W_E_63" vType="standard_car" speedFactor="0.99" vaporized=""/>
    <tripinfo id="S_N_82" depart="797.00" departLane="E8_2" departPos="5.10" departSpeed="10.00" departDelay="0.00" arrival="966.00" arrivalLane="E23_0" arrivalPos="251.04" arrivalSpeed="13.81" duration="169.00" routeLength="1151.00" waitingTime="57.00" waitingCount="1" stopTime="0.00" timeLoss="84.19" rerouteNo="0" devices="tripinfo_S_N_82" vType="standard_car" speedFactor="1.02" vaporized=""/>
    <tripinfo id="S_N_80" depart="789.00" departLane="E8_1" departPos="5.10" departSpeed="10.00" departDelay="0.00" arrival="984.00" arrivalLane="E23_0" arrivalPos="251.04" arrivalSpeed="14.14" duration="195.00" routeLength="1151.00" waitingTime="64.00" waitingCount="2" stopTime="0.00" timeLoss="112.05" rerouteNo="0" devices="tripinfo_S_N_80" vType="standard_car" speedFactor="1.03" vaporized=""/>
    <tripinfo id="W_E_74" depart="776.00" departLane="E9_0" departPos="5.10" departSpeed="10.00" departDelay="0.00" arrival="988.00" arrivalLane="E22_0" arrivalPos="258.43" arrivalSpeed="13.04" duration="212.00" routeLength="1065.97" waitingTime="95.00" waitingCount="2" stopTime="0.00" timeLoss="128.83" rerouteNo="0" devices="tripinfo_W_E_74" vType="standard_car" speedFactor="0.96" vaporized=""/>
    <tripinfo id="W_S_71" depart="770.00" departLane="E9_2" departPos="5.10" departSpeed="10.00" departDelay="0.00" arrival="990.00" arrivalLane="E23_0" arrivalPos="251.04" arrivalSpeed="13.13" duration="220.00" routeLength="1083.25" waitingTime="92.00" waitingCount="5" stopTime="0.00" timeLoss="137.63" rerouteNo="0" devices="tripinfo_W_S_71" vType="standard_car" speedFactor="0.97" vaporized=""/>
    <tripinfo id="N_E_95" depart="866.00" departLane="E10_1" departPos="5.10" departSpeed="10.00" departDelay="0.00" arrival="991.00" arrivalLane="E23_0" arrivalPos="251.04" arrivalSpeed="13.87" duration="125.00" routeLength="1017.15" waitingTime="29.00" waitingCount="2" stopTime="0.00" timeLoss="54.55" rerouteNo="0" devices="tripinfo_N_E_95" vType="standard_car" speedFactor="1.06" vaporized=""/>
    <tripinfo id="N_E_97" depart="893.00" departLane="E10_0" departPos="5.10" departSpeed="10.00" departDelay="0.00" arrival="998.00" arrivalLane="E23_0" arrivalPos="251.04" arrivalSpeed="12.18" duration="105.00" routeLength="1017.15" waitingTime="4.00" waitingCount="3" stopTime="0.00" timeLoss="22.99" rerouteNo="0" devices="tripinfo_N_E_97" vType="standard_car" speedFactor="0.91" vaporized=""/>
    <tripinfo id="E_W_69" depart="759.00" departLane="E11_2" departPos="5.10" departSpeed="10.00" departDelay="0.00" arrival="1004.00" arrivalLane="E21_0" arrivalPos="182.45" arrivalSpeed="14.09" duration="245.00" routeLength="1081.57" waitingTime="109.00" waitingCount="5" stopTime="0.00" timeLoss="165.86" rerouteNo="0" devices="tripinfo_E_W_69" vType="standard_car" speedFactor="1.02" vaporized=""/>
    <tripinfo id="N_S_96" depart="876.00" departLane="E10_0" departPos="5.10" departSpeed="10.00" departDelay="0.00" arrival="1008.00" arrivalLane="E24_0" arrivalPos="229.28" arrivalSpeed="13.84" duration="132.00" routeLength="1051.83" waitingTime="18.00" waitingCount="2" stopTime="0.00" timeLoss="54.96" rerouteNo="0" devices="tripinfo_N_S_96" vType="standard_car" speedFactor="1.01" vaporized=""/>
    <tripinfo id="E_N_98" depart="902.00" departLane="E11_1" departPos="5.10" departSpeed="10.00" departDelay="0.00" arrival="1008.00" arrivalLane="E22_0" arrivalPos="258.43" arrivalSpeed="15.21" duration="106.00" routeLength="924.43" waitingTime="30.00" waitingCount="1" stopTime="0.00" timeLoss="44.84" rerouteNo="0" devices="tripinfo_E_N_98" vType="standard_car" speedFactor="1.12" vaporized=""/>
    <tripinfo id="E_W_85" depart="810.00" departLane="E11_2" departPos="5.10" departSpeed="10.00" departDelay="0.00" arrival="1013.00" arrivalLane="E21_0" arrivalPos="182.45" arrivalSpeed="13.48" duration="203.00" routeLength="1078.04" waitingTime="79.00" waitingCount="2" stopTime="0.00" timeLoss="120.47" rerouteNo="0" devices="tripinfo_E_W_85" vType="standard_car" speedFactor="0.98" vaporized=""/>
    <tripinfo id="W_E_89" depart="826.00" departLane="E9_2" departPos="5.10" departSpeed="10.00" departDelay="0.00" arrival="1018.00" arrivalLane="E22_0" arrivalPos="258.43" arrivalSpeed="14.00" duration="192.00" routeLength="1065.97" waitingTime="83.00" waitingCount="2" stopTime="0.00" timeLoss="114.69" rerouteNo="0" devices="tripinfo_W_E_89" vType="standard_car" speedFactor="1.02" vaporized=""/>
    <tripinfo id="S_E_102" depart="927.00" departLane="E8_0" departPos="5.10" departSpeed="10.00" departDelay="0.00" arrival="1021.00" arrivalLane="E24_0" arrivalPos="229.28" arrivalSpeed="13.12" duration="94.00" routeLength="905.97" waitingTime="15.00" waitingCount="1" stopTime="0.00" timeLoss="25.14" rerouteNo="0" devices="tripinfo_S_E_102" vType="standard_car" speedFactor="0.97" vaporized=""/>
    <tripinfo id="W_S_93" depart="854.00" departLane="E9_0" departPos="5.10" departSpeed="10.00" departDelay="0.00" arrival="1024.00" arrivalLane="E23_0" arrivalPos="251.04" arrivalSpeed="12.74" duration="170.00" routeLength="1083.25" waitingTime="52.00" waitingCount="2" stopTime="0.00" timeLoss="83.21" rerouteNo="0" devices="tripinfo_W_S_93" vType="standard_car" speedFactor="0.92" vaporized=""/>
    <tripinfo id="W_E_94" depart="862.00" departLane="E9_0" departPos="5.10" departSpeed="10.00" departDelay="0.00" arrival="1028.00" arrivalLane="E22_0" arrivalPos="258.43" arrivalSpeed="14.84" duration="166.00" routeLength="1065.97" waitingTime="54.00" waitingCount="3" stopTime="0.00" timeLoss="94.11" rerouteNo="0" devices="tripinfo_W_E_94" vType="standard_car" speedFactor="1.09" vaporized=""/>
    <tripinfo id="W_S_78" depart="784.00" departLane="E9_2" departPos="5.10" departSpeed="10.00" departDelay="0.00" arrival="1031.00" arrivalLane="E23_0" arrivalPos="251.04" arrivalSpeed="13.71" duration="247.00" routeLength="1083.25" waitingTime="115.00" waitingCount="3" stopTime="0.00" timeLoss="168.06" rerouteNo="0" devices="tripinfo_W_S_78" vType="standard_car" speedFactor="1.01" vaporized=""/>
    <tripinfo id="W_N_108" depart="943.00" departLane="E9_0" departPos="5.10" departSpeed="10.00" departDelay="1.00" arrival="1033.00" arrivalLane="E21_0" arrivalPos="182.45" arrivalSpeed="14.36" duration="90.00" routeLength="935.42" waitingTime="11.00" waitingCount="1" stopTime="0.00" timeLoss="25.60" rerouteNo="0" devices="tripinfo_W_N_108" vType="standard_car" speedFactor="1.06" vaporized=""/>
    <tripinfo id="E_W_83" depart="808.00" departLane="E11_2" departPos="5.10" departSpeed="10.00" departDelay="0.00" arrival="1035.00" arrivalLane="E21_1" arrivalPos="182.45" arrivalSpeed="13.01" duration="227.00" routeLength="1081.57" waitingTime="96.00" waitingCount="5" stopTime="0.00" timeLoss="142.34" rerouteNo="0" devices="tripinfo_E_W_83" vType="standard_car" speedFactor="0.97" vaporized=""/>
    <tripinfo id="E_S_106" depart="941.00" departLane="E11_2" departPos="5.10" departSpeed="10.00" departDelay="0.00" arrival="1042.00" arrivalLane="E24_0" arrivalPos="229.28" arrivalSpeed="13.93" duration="101.00" routeLength="984.21" waitingTime="6.00" waitingCount="1" stopTime="0.00" timeLoss="28.33" rerouteNo="0" devices="tripinfo_E_S_106" vType="standard_car" speedFactor="1.01" vaporized=""/>
    <tripinfo id="E_W_67" depart="753.00" departLane="E11_0" departPos="5.10" departSpeed="10.00" departDelay="0.00" arrival="1043.00" arrivalLane="E21_0" arrivalPos="182.45" arrivalSpeed="12.29" duration="290.00" routeLength="1081.57" waitingTime="127.00" waitingCount="7" stopTime="0.00" timeLoss="200.65" rerouteNo="0" devices="tripinfo_E_W_67" vType="standard_car" speedFactor="0.91" vaporized=""/>
    <tripinfo id="S_E_115" depart="962.00" departLane="E8_1" departPos="5.10" departSpeed="10.00" departDelay="0.00" arrival="1050.00" arrivalLane="E24_0" arrivalPos="229.28" arrivalSpeed="12.49" duration="88.00" routeLength="905.97" waitingTime="5.00" waitingCount="1" stopTime="0.00" timeLoss="16.34" rerouteNo="0" devices="tripinfo_S_E_115" vType="standard_car" speedFactor="0.92" vaporized=""/>
    <tripinfo id="N_E_110" depart="949.00" departLane="E10_0" departPos="5.10" departSpeed="10.00" departDelay="0.00" arrival="1052.00" arrivalLane="E23_0" arrivalPos="251.04" arrivalSpeed="12.50" duration="103.00" routeLength="1017.15" waitingTime="6.00" waitingCount="1" stopTime="0.00" timeLoss="22.69" rerouteNo="0" devices="tripinfo_N_E_110" vType="standard_car" speedFactor="0.93" vaporized=""/>
    <tripinfo id="S_E_118" depart="972.00" departLane="E8_0" departPos="5.10" departSpeed="10.00" departDelay="0.00" arrival="1052.00" arrivalLane="E24_0" arrivalPos="229.28" arrivalSpeed="13.50" duration="80.00" routeLength="905.97" waitingTime="0.00" waitingCount="0" stopTime="0.00" timeLoss="12.90" rerouteNo="0" devices="tripinfo_S_E_118" vType="standard_car" speedFactor="0.99" vaporized=""/>
    <tripinfo id="S_N_99" depart="909.00" departLane="E8_1" departPos="5.10" departSpeed="10.00" departDelay="0.00" arrival="1054.00" arrivalLane="E23_0" arrivalPos="251.04" arrivalSpeed="14.80" duration="145.00" routeLength="1151.00" waitingTime="32.00" waitingCount="2" stopTime="0.00" timeLoss="65.97" rerouteNo="0" devices="tripinfo_S_N_99" vType="standard_car" speedFactor="1.10" vaporized=""/>
    <tripinfo id="S_E_125" depart="991.00" departLane="E8_2" departPos="5.10" departSpeed="10.00" departDelay="0.00" arrival="1054.00" arrivalLane="E24_0" arrivalPos="229.28" arrivalSpeed="15.71" duration="63.00" routeLength="905.97" waitingTime="0.00" waitingCount="0" stopTime="0.00" timeLoss="5.11" rerouteNo="0" devices="tripinfo_S_E_125" vType="standard_car" speedFactor="1.15" vaporized=""/>
    <tripinfo id="W_S_91" depart="832.00" departLane="E9_1" departPos="5.10" departSpeed="10.00" departDelay="0.00" arrival="1062.00" arrivalLane="E23_0" arrivalPos="251.04" arrivalSpeed="12.30" duration="230.00" routeLength="1083.25" waitingTime="72.00" waitingCount="3" stopTime="0.00" timeLoss="140.56" rerouteNo="0" devices="tripinfo_W_S_91" vType="standard_car" speedFactor="0.89" vaporized=""/>
    <tripinfo id="N_E_122" depart="986.00" departLane="E10_1" departPos="5.10" departSpeed="10.00" departDelay="0.00" arrival="1064.00" arrivalLane="E23_0" arrivalPos="251.04" arrivalSpeed="14.03" duration="78.00" routeLength="1017.15" waitingTime="0.00" waitingCount="0" stopTime="0.00" timeLoss="5.59" rerouteNo="0" devices="tripinfo_N_E_122" vType="standard_car" speedFactor="1.03" vaporized=""/>
    <tripinfo id="E_W_73" depart="775.00" departLane="E11_0" departPos="5.10" departSpeed="10.00" departDelay="0.00" arrival="1070.00" arrivalLane="E21_1" arrivalPos="182.45" arrivalSpeed="14.57" duration="295.00" routeLength="1081.57" waitingTime="150.00" waitingCount="7" stopTime="0.00" timeLoss="218.12" rerouteNo="0" devices="tripinfo_E_W_73" vType="standard_car" speedFactor="1.06" vaporized=""/>
    <tripinfo id="E_S_112" depart="957.00" departLane="E11_0" departPos="5.10" departSpeed="10.00" departDelay="0.00" arrival="1072.00" arrivalLane="E24_0" arrivalPos="229.28" arrivalSpeed="14.81" duration="115.00" routeLength="984.21" waitingTime="24.00" waitingCount="2" stopTime="0.00" timeLoss="48.85" rerouteNo="0" devices="tripinfo_E_S_112" vType="standard_car" speedFactor="1.10" vaporized=""/>
    <tripinfo id="W_N_116" depart="970.00" departLane="E9_2" departPos="5.10" departSpeed="10.00" departDelay="0.00" arrival="1072.00" arrivalLane="E21_1" arrivalPos="182.45" arrivalSpeed="16.07" duration="102.00" routeLength="938.95" waitingTime="19.00" waitingCount="1" stopTime="0.00" timeLoss="43.03" rerouteNo="0" devices="tripinfo_W_N_116" vType="standard_car" speedFactor="1.18" vaporized=""/>
    <tripinfo id="E_W_86" depart="815.00" departLane="E11_0" departPos="5.10" departSpeed="10.00" departDelay="0.00" arrival="1075.00" arrivalLane="E21_0" arrivalPos="182.45" arrivalSpeed="13.52" duration="260.00" routeLength="1078.04" waitingTime="117.00" waitingCount="3" stopTime="0.00" timeLoss="179.32" rerouteNo="0" devices="tripinfo_E_W_86" vType="standard_car" speedFactor="1.00" vaporized=""/>
    <tripinfo id="E_W_103" depart="931.00" departLane="E11_0" departPos="5.10" departSpeed="10.00" departDelay="0.00" arrival="1076.00" arrivalLane="E21_1" arrivalPos="182.45" arrivalSpeed="13.19" duration="145.00" routeLength="1081.57" waitingTime="29.00" waitingCount="2" stopTime="0.00" timeLoss="59.30" rerouteNo="0" devices="tripinfo_E_W_103" vType="standard_car" speedFactor="0.95" vaporized=""/>
    <tripinfo id="N_S_109" depart="947.00" departLane="E10_1" departPos="5.10" departSpeed="10.00" departDelay="0.00" arrival="1077.00" arrivalLane="E24_0" arrivalPos="229.28" arrivalSpeed="13.28" duration="130.00" routeLength="1051.83" waitingTime="17.00" waitingCount="2" stopTime="0.00" timeLoss="48.82" rerouteNo="0" devices="tripinfo_N_S_109" vType="standard_car" speedFactor="0.96" vaporized=""/>
    <tripinfo id="N_S_105" depart="935.00" departLane="E10_1" departPos="5.10" departSpeed="10.00" departDelay="0.00" arrival="1080.00" arrivalLane="E24_0" arrivalPos="229.28" arrivalSpeed="14.79" duration="145.00" routeLength="1051.83" waitingTime="29.00" waitingCount="4" stopTime="0.00" timeLoss="72.16" rerouteNo="0" devices="tripinfo_N_S_105" vType="standard_car" speedFactor="1.07" vaporized=""/>
    <tripinfo id="E_N_130" depart="1008.00" departLane="E11_0" departPos="5.10" departSpeed="10.00" departDelay="0.00" arrival="1080.00" arrivalLane="E22_0" arrivalPos="258.43" arrivalSpeed="13.87" duration="72.00" routeLength="924.43" waitingTime="0.00" waitingCount="0" stopTime="0.00" timeLoss="5.12" rerouteNo="0" devices="tripinfo_E_N_130" vType="standard_car" speedFactor="1.03" vaporized=""/>
    <tripinfo id="E_N_134" depart="1017.00" departLane="E11_1" departPos="5.10" departSpeed="10.00" departDelay="0.00" arrival="1081.00" arrivalLane="E22_0" arrivalPos="258.43" arrivalSpeed="14.61" duration="64.00" routeLength="924.43" waitingTime="0.00" waitingCount="0" stopTime="0.00" timeLoss="8.94" rerouteNo="0" devices="tripinfo_E_N_134" vType="standard_car" speedFactor="1.23" vaporized=""/>
    <tripinfo id="E_W_104" depart="935.00" departLane="E11_2" departPos="5.10" departSpeed="10.00" departDelay="0.00" arrival="1083.00" arrivalLane="E21_0" arrivalPos="182.45" arrivalSpeed="12.30" duration="148.00" routeLength="1077.66" waitingTime="6.00" waitingCount="1" stopTime="0.00" timeLoss="57.81" rerouteNo="0" devices="tripinfo_E_W_104" vType="standard_car" speedFactor="0.89" vaporized=""/>
    <tripinfo id="E_S_123" depart="987.00" departLane="E11_1" departPos="5.10" departSpeed="10.00" departDelay="0.00" arrival="1085.00" arrivalLane="E24_0" arrivalPos="229.28" arrivalSpeed="14.00" duration="98.00" routeLength="984.21" waitingTime="10.00" waitingCount="1" stopTime="0.00" timeLoss="26.62" rerouteNo="0" devices="tripinfo_E_S_123" vType="standard_car" speedFactor="1.02" vaporized=""/>
    <tripinfo id="E_W_100" depart="910.00" departLane="E11_1" departPos="5.10" departSpeed="10.00" departDelay="0.00" arrival="1088.00" arrivalLane="E21_1" arrivalPos="182.45" arrivalSpeed="14.45" duration="178.00" routeLength="1081.57" waitingTime="47.00" waitingCount="4" stopTime="0.00" timeLoss="101.01" rerouteNo="0" devices="tripinfo_E_W_100" vType="standard_car" speedFactor="1.06" vaporized=""/>
    <tripinfo id="E_S_127" depart="997.00" departLane="E11_1" departPos="5.10" departSpeed="10.00" departDelay="0.00" arrival="1094.00" arrivalLane="E24_0" arrivalPos="229.28" arrivalSpeed="11.02" duration="97.00" routeLength="980.30" waitingTime="0.00" waitingCount="0" stopTime="0.00" timeLoss="8.86" rerouteNo="0" devices="tripinfo_E_S_127" vType="standard_car" speedFactor="0.82" vaporized=""/>
    <tripinfo id="S_W_120" depart="979.00" departLane="E8_1" departPos="5.10" departSpeed="10.00" departDelay="0.00" arrival="1096.00" arrivalLane="E21_0" arrivalPos="182.45" arrivalSpeed="12.79" duration="117.00" routeLength="1006.25" waitingTime="0.00" waitingCount="0" stopTime="0.00" timeLoss="37.90" rerouteNo="0" devices="tripinfo_S_W_120" vType="standard_car" speedFactor="0.94" vaporized=""/>
    <tripinfo id="S_W_113" depart="960.00" departLane="E8_0" departPos="5.10" departSpeed="10.00" departDelay="0.00" arrival="1100.00" arrivalLane="E21_1" arrivalPos="182.45" arrivalSpeed="13.55" duration="140.00" routeLength="1009.18" waitingTime="20.00" waitingCount="3" stopTime="0.00" timeLoss="64.74" rerouteNo="0" devices="tripinfo_S_W_113" vType="standard_car" speedFactor="1.01" vaporized=""/>
    <tripinfo id="E_N_136" depart="1033.00" departLane="E11_1" departPos="5.10" departSpeed="10.00" departDelay="0.00" arrival="1100.00" arrivalLane="E22_0" arrivalPos="258.43" arrivalSpeed="15.44" duration="67.00" routeLength="924.43" waitingTime="0.00" waitingCount="0" stopTime="0.00" timeLoss="5.63" rerouteNo="0" devices="tripinfo_E_N_136" vType="standard_car" speedFactor="1.12" vaporized=""/>
    <tripinfo id="S_N_101" depart="920.00" departLane="E8_2" departPos="5.10" departSpeed="10.00" departDelay="0.00" arrival="1109.00" arrivalLane="E23_0" arrivalPos="251.04" arrivalSpeed="13.04" duration="189.00" routeLength="1151.00" waitingTime="57.00" waitingCount="3" stopTime="0.00" timeLoss="99.74" rerouteNo="0" devices="tripinfo_S_N_101" vType="standard_car" speedFactor="0.96" vaporized=""/>
    <tripinfo id="W_S_107" depart="941.00" departLane="E9_0" departPos="5.10" departSpeed="10.00" departDelay="0.00" arrival="1111.00" arrivalLane="E23_0" arrivalPos="251.04" arrivalSpeed="14.27" duration="170.00" routeLength="1083.25" waitingTime="47.00" waitingCount="3" stopTime="0.00" timeLoss="92.26" rerouteNo="0" devices="tripinfo_W_S_107" vType="standard_car" speedFactor="1.03" vaporized=""/>
    <tripinfo id="E_W_114" depart="961.00" departLane="E11_2" departPos="5.10" departSpeed="10.00" departDelay="0.00" arrival="1115.00" arrivalLane="E21_1" arrivalPos="182.45" arrivalSpeed="14.75" duration="154.00" routeLength="1081.57" waitingTime="39.00" waitingCount="2" stopTime="0.00" timeLoss="79.60" rerouteNo="0" devices="tripinfo_E_W_114" vType="standard_car" speedFactor="1.10" vaporized=""/>
    <tripinfo id="S_N_111" depart="956.00" departLane="E8_2" departPos="5.10" departSpeed="10.00" departDelay="0.00" arrival="1119.00" arrivalLane="E23_0" arrivalPos="251.04" arrivalSpeed="11.97" duration="163.00" routeLength="1151.00" waitingTime="15.00" waitingCount="4" stopTime="0.00" timeLoss="63.22" rerouteNo="0" devices="tripinfo_S_N_111" vType="standard_car" speedFactor="0.87" vaporized=""/>
    <tripinfo id="W_E_126" depart="995.00" departLane="E9_1" departPos="5.10" departSpeed="10.00" departDelay="0.00" arrival="1119.00" arrivalLane="E22_0" arrivalPos="258.43" arrivalSpeed="14.09" duration="124.00" routeLength="1065.97" waitingTime="12.00" waitingCount="3" stopTime="0.00" timeLoss="48.15" rerouteNo="0" devices="tripinfo_W_E_126" vType="standard_car" speedFactor="1.03" vaporized=""/>
    <tripinfo id="E_W_128" depart="1001.00" departLane="E11_1" departPos="5.10" departSpeed="10.00" departDelay="0.00" arrival="1119.00" arrivalLane="E21_1" arrivalPos="182.45" arrivalSpeed="15.10" duration="118.00" routeLength="1081.57" waitingTime="7.00" waitingCount="2" stopTime="0.00" timeLoss="44.11" rerouteNo="0" devices="tripinfo_E_W_128" vType="standard_car" speedFactor="1.12" vaporized=""/>
    <tripinfo id="E_S_135" depart="1028.00" departLane="E11_0" departPos="5.10" departSpeed="10.00" departDelay="0.00" arrival="1120.00" arrivalLane="E24_0" arrivalPos="229.28" arrivalSpeed="13.79" duration="92.00" routeLength="984.21" waitingTime="7.00" waitingCount="1" stopTime="0.00" timeLoss="20.01" rerouteNo="0" devices="tripinfo_E_S_135" vType="standard_car" speedFactor="1.01" vaporized=""/>
    <tripinfo id="E_W_117" depart="972.00" departLane="E11_1" departPos="5.10" departSpeed="10.00" departDelay="0.00" arrival="1123.00" arrivalLane="E21_1" arrivalPos="182.45" arrivalSpeed="13.50" duration="151.00" routeLength="1081.57" waitingTime="33.00" waitingCount="2" stopTime="0.00" timeLoss="70.01" rerouteNo="0" devices="tripinfo_E_W_117" vType="standard_car" speedFactor="1.00" vaporized=""/>
    <tripinfo id="E_W_121" depart="984.00" departLane="E11_0" departPos="5.10" departSpeed="10.00" departDelay="0.00" arrival="1126.00" arrivalLane="E21_1" arrivalPos="182.45" arrivalSpeed="15.22" duration="142.00" routeLength="1081.57" waitingTime="25.00" waitingCount="2" stopTime="0.00" timeLoss="68.36" rerouteNo="0" devices="tripinfo_E_W_121" vType="standard_car" speedFactor="1.10" vaporized=""/>
    <tripinfo id="E_W_133" depart="1010.00" departLane="E11_1" departPos="5.10" departSpeed="10.00" departDelay="0.00" arrival="1132.00" arrivalLane="E21_0" arrivalPos="182.45" arrivalSpeed="13.99" duration="122.00" routeLength="1081.57" waitingTime="5.00" waitingCount="2" stopTime="0.00" timeLoss="42.76" rerouteNo="0" devices="tripinfo_E_W_133" vType="standard_car" speedFactor="1.04" vaporized=""/>
    <tripinfo id="S_E_142" depart="1066.00" departLane="E8_1" departPos="5.10" departSpeed="10.00" departDelay="0.00" arrival="1156.00" arrivalLane="E24_0" arrivalPos="229.28" arrivalSpeed="12.83" duration="90.00" routeLength="905.97" waitingTime="7.00" waitingCount="1" stopTime="0.00" timeLoss="18.56" rerouteNo="0" devices="tripinfo_S_E_142" vType="standard_car" speedFactor="0.94" vaporized=""/>
    <tripinfo id="W_E_129" depart="1004.00" departLane="E9_2" departPos="5.10" departSpeed="10.00" departDelay="0.00" arrival="1162.00" arrivalLane="E22_0" arrivalPos="258.43" arrivalSpeed="13.81" duration="158.00" routeLength="1065.97" waitingTime="41.00" waitingCount="3" stopTime="0.00" timeLoss="79.23" rerouteNo="0" devices="tripinfo_W_E_129" vType="standard_car" speedFactor="1.01" vaporized=""/>
    <tripinfo id="S_N_119" depart="974.00" departLane="E8_0" departPos="5.10" departSpeed="10.00" departDelay="0.00" arrival="1164.00" arrivalLane="E23_0" arrivalPos="251.04" arrivalSpeed="14.68" duration="190.00" routeLength="1151.00" waitingTime="44.00" waitingCount="6" stopTime="0.00" timeLoss="109.39" rerouteNo="0" devices="tripinfo_S_N_119" vType="standard_car" speedFactor="1.07" vaporized=""/>
    <tripinfo id="W_E_132" depart="1011.00" departLane="E9_2" departPos="5.10" departSpeed="10.00" departDelay="2.00" arrival="1167.00" arrivalLane="E22_0" arrivalPos="258.43" arrivalSpeed="12.89" duration="156.00" routeLength="1065.97" waitingTime="42.00" waitingCount="3" stopTime="0.00" timeLoss="73.91" rerouteNo="0" devices="tripinfo_W_E_132" vType="standard_car" speedFactor="0.96" vaporized=""/>
    <tripinfo id="W_S_131" depart="1009.00" departLane="E9_2" departPos="5.10" departSpeed="10.00" departDelay="0.00" arrival="1169.00" arrivalLane="E23_0" arrivalPos="251.04" arrivalSpeed="14.66" duration="160.00" routeLength="1083.25" waitingTime="37.00" waitingCount="3" stopTime="0.00" timeLoss="85.34" rerouteNo="0" devices="tripinfo_W_S_131" vType="standard_car" speedFactor="1.07" vaporized=""/>
    <tripinfo id="W_E_124" depart="990.00" departLane="E9_0" departPos="5.10" departSpeed="10.00" departDelay="0.00" arrival="1173.00" arrivalLane="E22_0" arrivalPos="258.43" arrivalSpeed="14.47" duration="183.00" routeLength="1065.97" waitingTime="47.00" waitingCount="7" stopTime="0.00" timeLoss="108.62" rerouteNo="0" devices="tripinfo_W_E_124" vType="standard_car" speedFactor="1.06" vaporized=""/>
    <tripinfo id="W_N_145" depart="1078.00" departLane="E9_0" departPos="5.10" departSpeed="10.00" departDelay="0.00" arrival="1176.00" arrivalLane="E21_1" arrivalPos="182.45" arrivalSpeed="15.47" duration="98.00" routeLength="941.43" waitingTime="24.00" waitingCount="1" stopTime="0.00" timeLoss="36.97" rerouteNo="0" devices="tripinfo_W_N_145" vType="standard_car" speedFactor="1.14" vaporized=""/>
    <tripinfo id="W_E_139" depart="1051.00" departLane="E9_0" departPos="5.10" departSpeed="10.00" departDelay="0.00" arrival="1178.00" arrivalLane="E22_0" arrivalPos="258.43" arrivalSpeed="12.81" duration="127.00" routeLength="1065.97" waitingTime="18.00" waitingCount="3" stopTime="0.00" timeLoss="44.90" rerouteNo="0" devices="tripinfo_W_E_139" vType="standard_car" speedFactor="0.95" vaporized=""/>
    <tripinfo id="W_E_143" depart="1068.00" departLane="E9_1" departPos="5.10" departSpeed="10.00" departDelay="0.00" arrival="1193.00" arrivalLane="E22_0" arrivalPos="258.43" arrivalSpeed="15.44" duration="125.00" routeLength="1065.97" waitingTime="20.00" waitingCount="4" stopTime="0.00" timeLoss="54.65" rerouteNo="0" devices="tripinfo_W_E_143" vType="standard_car" speedFactor="1.13" vaporized=""/>
    <tripinfo id="N_E_138" depart="1048.00" departLane="E10_1" departPos="5.10" departSpeed="10.00" departDelay="0.00" arrival="1203.00" arrivalLane="E23_0" arrivalPos="251.04" arrivalSpeed="13.94" duration="155.00" routeLength="1017.15" waitingTime="42.00" waitingCount="5" stopTime="0.00" timeLoss="81.01" rerouteNo="0" devices="tripinfo_N_E_138" vType="standard_car" speedFactor="1.00" vaporized=""/>
    <tripinfo id="W_N_148" depart="1096.00" departLane="E9_2" departPos="5.10" departSpeed="10.00" departDelay="0.00" arrival="1207.00" arrivalLane="E21_0" arrivalPos="182.45" arrivalSpeed="13.06" duration="111.00" routeLength="941.43" waitingTime="15.00" waitingCount="2" stopTime="0.00" timeLoss="39.42" rerouteNo="0" devices="tripinfo_W_N_148" vType="standard_car" speedFactor="0.97" vaporized=""/>
    <tripinfo id="E_S_154" depart="1103.00" departLane="E11_0" departPos="5.10" departSpeed="10.00" departDelay="0.00" arrival="1207.00" arrivalLane="E24_0" arrivalPos="229.28" arrivalSpeed="14.57" duration="104.00" routeLength="984.21" waitingTime="8.00" waitingCount="2" stopTime="0.00" timeLoss="35.54" rerouteNo="0" devices="tripinfo_E_S_154" vType="standard_car" speedFactor="1.06" vaporized=""/>
    <tripinfo id="E_N_164" depart="1138.00" departLane="E11_0" departPos="5.10" departSpeed="10.00" departDelay="0.00" arrival="1208.00" arrivalLane="E22_0" arrivalPos="258.43" arrivalSpeed="14.52" duration="70.00" routeLength="924.43" waitingTime="0.00" waitingCount="0" stopTime="0.00" timeLoss="5.05" rerouteNo="0" devices="tripinfo_E_N_164" vType="standard_car" speedFactor="1.05" vaporized=""/>
    <tripinfo id="N_S_137" depart="1035.00" departLane="E10_0" departPos="5.10" departSpeed="10.00" departDelay="0.00" arrival="1214.00" arrivalLane="E24_0" arrivalPos="229.28" arrivalSpeed="13.77" duration="179.00" routeLength="1051.83" waitingTime="45.00" waitingCount="3" stopTime="0.00" timeLoss="101.99" rerouteNo="0" devices="tripinfo_N_S_137" vType="standard_car" speedFactor="1.02" vaporized=""/>
    <tripinfo id="E_S_146" depart="1085.00" departLane="E11_2" departPos="5.10" departSpeed="10.00" departDelay="0.00" arrival="1220.00" arrivalLane="E24_0" arrivalPos="229.28" arrivalSpeed="12.25" duration="135.00" routeLength="984.21" waitingTime="24.00" waitingCount="5" stopTime="0.00" timeLoss="52.31" rerouteNo="0" devices="tripinfo_E_S_146" vType="standard_car" speedFactor="0.89" vaporized=""/>
    <tripinfo id="N_W_140" depart="1055.00" departLane="E10_1" departPos="5.10" departSpeed="10.00" departDelay="0.00" arrival="1222.00" arrivalLane="E22_0" arrivalPos="258.43" arrivalSpeed="15.24" duration="167.00" routeLength="999.87" waitingTime="48.00" waitingCount="3" stopTime="0.00" timeLoss="100.23" rerouteNo="0" devices="tripinfo_N_W_140" vType="standard_car" speedFactor="1.11" vaporized=""/>
    <tripinfo id="S_N_141" depart="1062.00" departLane="E8_2" departPos="5.10" departSpeed="10.00" departDelay="0.00" arrival="1231.00" arrivalLane="E23_0" arrivalPos="251.04" arrivalSpeed="15.98" duration="169.00" routeLength="1151.00" waitingTime="39.00" waitingCount="5" stopTime="0.00" timeLoss="95.09" rerouteNo="0" devices="tripinfo_S_N_141" vType="standard_car" speedFactor="1.16" vaporized=""/>
    <tripinfo id="N_W_144" depart="1077.00" departLane="E10_0" departPos="5.10" departSpeed="10.00" departDelay="0.00" arrival="1234.00" arrivalLane="E22_0" arrivalPos="258.43" arrivalSpeed="9.83" duration="157.00" routeLength="999.87" waitingTime="28.00" waitingCount="3" stopTime="0.00" timeLoss="56.72" rerouteNo="0" devices="tripinfo_N_W_144" vType="standard_car" speedFactor="0.73" vaporized=""/>
    <tripinfo id="N_W_149" depart="1100.00" departLane="E10_1" departPos="5.10" departSpeed="10.00" departDelay="0.00" arrival="1237.00" arrivalLane="E22_0" arrivalPos="258.43" arrivalSpeed="14.27" duration="137.00" routeLength="999.87" waitingTime="21.00" waitingCount="6" stopTime="0.00" timeLoss="66.09" rerouteNo="0" devices="tripinfo_N_W_149" vType="standard_car" speedFactor="1.04" vaporized=""/>
    <tripinfo id="N_E_150" depart="1102.00" departLane="E10_1" departPos="5.10" departSpeed="10.00" departDelay="1.00" arrival="1238.00" arrivalLane="E23_0" arrivalPos="251.04" arrivalSpeed="12.89" duration="136.00" routeLength="1017.15" waitingTime="25.00" waitingCount="3" stopTime="0.00" timeLoss="58.22" rerouteNo="0" devices="tripinfo_N_E_150" vType="standard_car" speedFactor="0.96" vaporized=""/>
    <tripinfo id="W_E_147" depart="1090.00" departLane="E9_1" departPos="5.10" departSpeed="10.00" departDelay="0.00" arrival="1240.00" arrivalLane="E22_0" arrivalPos="258.43" arrivalSpeed="13.44" duration="150.00" routeLength="1065.97" waitingTime="28.00" waitingCount="3" stopTime="0.00" timeLoss="71.60" rerouteNo="0" devices="tripinfo_W_E_147" vType="standard_car" speedFactor="1.00" vaporized=""/>
    <tripinfo id="N_E_153" depart="1104.00" departLane="E10_0" departPos="5.10" departSpeed="10.00" departDelay="1.00" arrival="1242.00" arrivalLane="E23_0" arrivalPos="251.04" arrivalSpeed="12.58" duration="138.00" routeLength="1017.15" waitingTime="24.00" waitingCount="3" stopTime="0.00" timeLoss="57.22" rerouteNo="0" devices="tripinfo_N_E_153" vType="standard_car" speedFactor="0.93" vaporized=""/>
    <tripinfo id="W_S_155" depart="1104.00" departLane="E9_0" departPos="5.10" departSpeed="10.00" departDelay="0.00" arrival="1243.00" arrivalLane="E23_1" arrivalPos="251.04" arrivalSpeed="15.28" duration="139.00" routeLength="1083.25" waitingTime="19.00" waitingCount="4" stopTime="0.00" timeLoss="67.87" rerouteNo="0" devices="tripinfo_W_S_155" vType="standard_car" speedFactor="1.12" vaporized=""/>
    <tripinfo id="S_N_152" depart="1103.00" departLane="E8_1" departPos="5.10" departSpeed="10.00" departDelay="0.00" arrival="1246.00" arrivalLane="E23_0" arrivalPos="251.04" arrivalSpeed="14.74" duration="143.00" routeLength="1151.00" waitingTime="13.00" waitingCount="3" stopTime="0.00" timeLoss="62.83" rerouteNo="0" devices="tripinfo_S_N_152" vType="standard_car" speedFactor="1.07" vaporized=""/>
    <tripinfo id="N_W_162" depart="1133.00" departLane="E10_1" departPos="5.10" departSpeed="10.00" departDelay="0.00" arrival="1248.00" arrivalLane="E22_0" arrivalPos="258.43" arrivalSpeed="13.29" duration="115.00" routeLength="999.87" waitingTime="9.00" waitingCount="1" stopTime="0.00" timeLoss="40.57" rerouteNo="0" devices="tripinfo_N_W_162" vType="standard_car" speedFactor="0.99" vaporized=""/>
    <tripinfo id="N_S_158" depart="1115.00" departLane="E10_1" departPos="5.10" departSpeed="10.00" departDelay="0.00" arrival="1268.00" arrivalLane="E24_0" arrivalPos="229.28" arrivalSpeed="12.44" duration="153.00" routeLength="1051.83" waitingTime="24.00" waitingCount="2" stopTime="0.00" timeLoss="67.16" rerouteNo="0" devices="tripinfo_N_S_158" vType="standard_car" speedFactor="0.91" vaporized=""/>
    <tripinfo id="W_E_151" depart="1102.00" departLane="E9_2" departPos="5.10" departSpeed="10.00" departDelay="0.00" arrival="1276.00" arrivalLane="E22_0" arrivalPos="258.43" arrivalSpeed="13.68" duration="174.00" routeLength="1065.97" waitingTime="60.00" waitingCount="3" stopTime="0.00" timeLoss="95.93" rerouteNo="0" devices="tripinfo_W_E_151" vType="standard_car" speedFactor="1.00" vaporized=""/>
    <tripinfo id="S_E_169" depart="1185.00" departLane="E8_0" departPos="5.10" departSpeed="10.00" departDelay="0.00" arrival="1280.00" arrivalLane="E24_0" arrivalPos="229.28" arrivalSpeed="12.95" duration="95.00" routeLength="905.97" waitingTime="13.00" waitingCount="1" stopTime="0.00" timeLoss="23.85" rerouteNo="0" devices="tripinfo_S_E_169" vType="standard_car" speedFactor="0.94" vaporized=""/>
    <tripinfo id="W_S_157" depart="1110.00" departLane="E9_0" departPos="5.10" departSpeed="10.00" departDelay="0.00" arrival="1285.00" arrivalLane="E23_0" arrivalPos="251.04" arrivalSpeed="14.70" duration="175.00" routeLength="1083.25" waitingTime="56.00" waitingCount="2" stopTime="0.00" timeLoss="101.19" rerouteNo="0" devices="tripinfo_W_S_157" vType="standard_car" speedFactor="1.08" vaporized=""/>
    <tripinfo id="N_S_170" depart="1190.00" departLane="E10_0" departPos="5.10" departSpeed="10.00" departDelay="0.00" arrival="1287.00" arrivalLane="E24_0" arrivalPos="229.28" arrivalSpeed="14.82" duration="97.00" routeLength="1051.83" waitingTime="6.00" waitingCount="1" stopTime="0.00" timeLoss="25.23" rerouteNo="0" devices="tripinfo_N_S_170" vType="standard_car" speedFactor="1.09" vaporized=""/>
    <tripinfo id="W_S_161" depart="1130.00" departLane="E9_1" departPos="5.10" departSpeed="10.00" departDelay="0.00" arrival="1290.00" arrivalLane="E23_0" arrivalPos="251.04" arrivalSpeed="14.62" duration="160.00" routeLength="1083.25" waitingTime="42.00" waitingCount="2" stopTime="0.00" timeLoss="86.21" rerouteNo="0" devices="tripinfo_W_S_161" vType="standard_car" speedFactor="1.08" vaporized=""/>
    <tripinfo id="S_N_159" depart="1116.00" departLane="E8_1" departPos="5.10" departSpeed="10.00" departDelay="0.00" arrival="1292.00" arrivalLane="E23_0" arrivalPos="251.04" arrivalSpeed="15.40" duration="176.00" routeLength="1151.00" waitingTime="52.00" waitingCount="4" stopTime="0.00" timeLoss="100.60" rerouteNo="0" devices="tripinfo_S_N_159" vType="standard_car" speedFactor="1.14" vaporized=""/>
    <tripinfo id="E_W_163" depart="1136.00" departLane="E11_1" departPos="5.10" departSpeed="10.00" departDelay="0.00" arrival="1292.00" arrivalLane="E21_0" arrivalPos="182.45" arrivalSpeed="15.31" duration="156.00" routeLength="1081.57" waitingTime="39.00" waitingCount="1" stopTime="0.00" timeLoss="83.17" rerouteNo="0" devices="tripinfo_E_W_163" vType="standard_car" speedFactor="1.13" vaporized=""/>
    <tripinfo id="E_W_156" depart="1109.00" departLane="E11_0" departPos="5.10" departSpeed="10.00" departDelay="0.00" arrival="1296.00" arrivalLane="E21_1" arrivalPos="182.45" arrivalSpeed="15.93" duration="187.00" routeLength="1081.57" waitingTime="57.00" waitingCount="2" stopTime="0.00" timeLoss="118.32" rerouteNo="0" devices="tripinfo_E_W_156" vType="standard_car" speedFactor="1.18" vaporized=""/>
    <tripinfo id="E_N_177" depart="1226.00" departLane="E11_0" departPos="5.10" departSpeed="10.00" departDelay="0.00" arrival="1298.00" arrivalLane="E22_0" arrivalPos="258.43" arrivalSpeed="14.26" duration="72.00" routeLength="924.43" waitingTime="0.00" waitingCount="0" stopTime="0.00" timeLoss="5.05" rerouteNo="0" devices="tripinfo_E_N_177" vType="standard_car" speedFactor="1.03" vaporized=""/>
    <tripinfo id="S_N_166" depart="1162.00" departLane="E8_1" departPos="5.10" departSpeed="10.00" departDelay="0.00" arrival="1310.00" arrivalLane="E23_0" arrivalPos="251.04" arrivalSpeed="13.49" duration="148.00" routeLength="1151.00" waitingTime="15.00" waitingCount="1" stopTime="0.00" timeLoss="62.83" rerouteNo="0" devices="tripinfo_S_N_166" vType="standard_car" speedFactor="1.00" vaporized=""/>
    <tripinfo id="S_N_160" depart="1123.00" departLane="E8_1" departPos="5.10" departSpeed="10.00" departDelay="0.00" arrival="1314.00" arrivalLane="E23_0" arrivalPos="251.04" arrivalSpeed="11.84" duration="191.00" routeLength="1151.00" waitingTime="56.00" waitingCount="3" stopTime="0.00" timeLoss="93.05" rerouteNo="0" devices="tripinfo_S_N_160" vType="standard_car" speedFactor="0.88" vaporized=""/>
    <tripinfo id="W_S_167" depart="1171.00" departLane="E9_2" departPos="5.10" departSpeed="10.00" departDelay="0.00" arrival="1315.00" arrivalLane="E23_1" arrivalPos="251.04" arrivalSpeed="14.12" duration="144.00" routeLength="1083.25" waitingTime="30.00" waitingCount="2" stopTime="0.00" timeLoss="66.28" rerouteNo="0" devices="tripinfo_W_S_167" vType="standard_car" speedFactor="1.03" vaporized=""/>
    <tripinfo id="N_E_172" depart="1211.00" departLane="E10_1" departPos="5.10" departSpeed="10.00" departDelay="0.00" arrival="1320.00" arrivalLane="E23_0" arrivalPos="251.04" arrivalSpeed="12.08" duration="109.00" routeLength="1017.15" waitingTime="12.00" waitingCount="1" stopTime="0.00" timeLoss="25.57" rerouteNo="0" devices="tripinfo_N_E_172" vType="standard_car" speedFactor="0.89" vaporized=""/>
    <tripinfo id="N_W_174" depart="1218.00" departLane="E10_0" departPos="5.10" departSpeed="10.00" departDelay="0.00" arrival="1322.00" arrivalLane="E22_0" arrivalPos="258.43" arrivalSpeed="13.26" duration="104.00" routeLength="999.87" waitingTime="10.00" waitingCount="1" stopTime="0.00" timeLoss="27.09" rerouteNo="0" devices="tripinfo_N_W_174" vType="standard_car" speedFactor="0.96" vaporized=""/>
    <tripinfo id="N_E_181" depart="1244.00" departLane="E10_0" departPos="5.10" departSpeed="10.00" departDelay="0.00" arrival="1322.00" arrivalLane="E23_0" arrivalPos="251.04" arrivalSpeed="14.11" duration="78.00" routeLength="1017.15" waitingTime="0.00" waitingCount="0" stopTime="0.00" timeLoss="5.34" rerouteNo="0" devices="tripinfo_N_E_181" vType="standard_car" speedFactor="1.03" vaporized=""/>
    <tripinfo id="N_S_182" depart="1245.00" departLane="E10_1" departPos="5.10" departSpeed="10.00" departDelay="1.00" arrival="1340.00" arrivalLane="E24_0" arrivalPos="229.28" arrivalSpeed="14.04" duration="95.00" routeLength="1051.83" waitingTime="2.00" waitingCount="1" stopTime="0.00" timeLoss="18.90" rerouteNo="0" devices="tripinfo_N_S_182" vType="standard_car" speedFactor="1.03" vaporized=""/>
    <tripinfo id="E_W_168" depart="1182.00" departLane="E11_0" departPos="5.10" departSpeed="10.00" departDelay="0.00" arrival="1342.00" arrivalLane="E21_0" arrivalPos="182.45" arrivalSpeed="13.33" duration="160.00" routeLength="1078.04" waitingTime="35.00" waitingCount="3" stopTime="0.00" timeLoss="77.47" rerouteNo="0" devices="tripinfo_E_W_168" vType="standard_car" speedFactor="0.98" vaporized=""/>
    <tripinfo id="E_N_184" depart="1253.00" departLane="E11_0" departPos="5.10" departSpeed="10.00" departDelay="0.00" arrival="1344.00" arrivalLane="E22_0" arrivalPos="258.43" arrivalSpeed="13.02" duration="91.00" routeLength="924.43" waitingTime="6.00" waitingCount="1" stopTime="0.00" timeLoss="18.25" rerouteNo="0" devices="tripinfo_E_N_184" vType="standard_car" speedFactor="0.94" vaporized=""/>
    <tripinfo id="W_E_176" depart="1223.00" departLane="E9_1" departPos="5.10" departSpeed="10.00" departDelay="0.00" arrival="1351.00" arrivalLane="E22_0" arrivalPos="258.43" arrivalSpeed="15.12" duration="128.00" routeLength="1065.97" waitingTime="29.00" waitingCount="1" stopTime="0.00" timeLoss="55.44" rerouteNo="0" devices="tripinfo_W_E_176" vType="standard_car" speedFactor="1.09" vaporized=""/>
    <tripinfo id="W_S_175" depart="1221.00" departLane="E9_2" departPos="5.10" departSpeed="10.00" departDelay="0.00" arrival="1357.00" arrivalLane="E23_0" arrivalPos="251.04" arrivalSpeed="12.40" duration="136.00" routeLength="1083.25" waitingTime="28.00" waitingCount="1" stopTime="0.00" timeLoss="49.51" rerouteNo="0" devices="tripinfo_W_S_175" vType="standard_car" speedFactor="0.92" vaporized=""/>
    <tripinfo id="S_N_179" depart="1231.00" departLane="E8_1" departPos="5.10" departSpeed="10.00" departDelay="0.00" arrival="1358.00" arrivalLane="E23_1" arrivalPos="251.04" arrivalSpeed="14.40" duration="127.00" routeLength="1151.00" waitingTime="16.00" waitingCount="1" stopTime="0.00" timeLoss="46.58" rerouteNo="0" devices="tripinfo_S_N_179" vType="standard_car" speedFactor="1.06" vaporized=""/>
    <tripinfo id="W_E_171" depart="1198.00" departLane="E9_0" departPos="5.10" departSpeed="10.00" departDelay="0.00" arrival="1360.00" arrivalLane="E22_0" arrivalPos="258.43" arrivalSpeed="12.33" duration="162.00" routeLength="1065.97" waitingTime="47.00" waitingCount="2" stopTime="0.00" timeLoss="73.88" rerouteNo="0" devices="tripinfo_W_E_171" vType="standard_car" speedFactor="0.90" vaporized=""/>
    <tripinfo id="N_E_186" depart="1274.00" departLane="E10_1" departPos="5.10" departSpeed="10.00" departDelay="0.00" arrival="1367.00" arrivalLane="E23_0" arrivalPos="251.04" arrivalSpeed="14.92" duration="93.00" routeLength="1017.15" waitingTime="8.00" waitingCount="1" stopTime="0.00" timeLoss="23.60" rerouteNo="0" devices="tripinfo_N_E_186" vType="standard_car" speedFactor="1.08" vaporized=""/>
    <tripinfo id="E_W_165" depart="1155.00" departLane="E11_2" departPos="5.10" departSpeed="10.00" departDelay="0.00" arrival="1451.00" arrivalLane="E21_0" arrivalPos="182.45" arrivalSpeed="12.36" duration="296.00" routeLength="1078.04" waitingTime="157.00" waitingCount="4" stopTime="0.00" timeLoss="207.58" rerouteNo="0" devices="tripinfo_E_W_165" vType="standard_car" speedFactor="0.91" vaporized=""/>
    <tripinfo id="N_S_185" depart="1265.00" departLane="E10_0" departPos="5.10" departSpeed="10.00" departDelay="0.00" arrival="1451.00" arrivalLane="E24_0" arrivalPos="229.28" arrivalSpeed="12.37" duration="186.00" routeLength="1051.83" waitingTime="78.00" waitingCount="2" stopTime="0.00" timeLoss="100.59" rerouteNo="0" devices="tripinfo_N_S_185" vType="standard_car" speedFactor="0.92" vaporized=""/>
    <tripinfo id="S_W_189" depart="1328.00" departLane="E8_1" departPos="5.10" departSpeed="10.00" departDelay="0.00" arrival="1455.00" arrivalLane="E21_1" arrivalPos="182.45" arrivalSpeed="13.21" duration="127.00" routeLength="1006.25" waitingTime="29.00" waitingCount="1" stopTime="0.00" timeLoss="50.76" rerouteNo="0" devices="tripinfo_S_W_189" vType="standard_car" speedFactor="0.97" vaporized=""/>
    <tripinfo id="W_E_173" depart="1216.00" departLane="E9_1" departPos="5.10" departSpeed="10.00" departDelay="0.00" arrival="1459.00" arrivalLane="E22_0" arrivalPos="258.43" arrivalSpeed="15.76" duration="243.00" routeLength="1065.97" waitingTime="136.00" waitingCount="3" stopTime="0.00" timeLoss="173.38" rerouteNo="0" devices="tripinfo_W_E_173" vType="standard_car" speedFactor="1.14" vaporized=""/>
    <tripinfo id="W_E_178" depart="1229.00" departLane="E9_1" departPos="5.10" departSpeed="10.00" departDelay="0.00" arrival="1462.00" arrivalLane="E22_0" arrivalPos="258.43" arrivalSpeed="14.62" duration="233.00" routeLength="1065.97" waitingTime="127.00" waitingCount="2" stopTime="0.00" timeLoss="160.38" rerouteNo="0" devices="tripinfo_W_E_178" vType="standard_car" speedFactor="1.08" vaporized=""/>
    <tripinfo id="W_E_180" depart="1234.00" departLane="E9_2" departPos="5.10" departSpeed="10.00" departDelay="0.00" arrival="1464.00" arrivalLane="E22_0" arrivalPos="258.43" arrivalSpeed="14.81" duration="230.00" routeLength="1065.97" waitingTime="126.00" waitingCount="2" stopTime="0.00" timeLoss="157.95" rerouteNo="0" devices="tripinfo_W_E_180" vType="standard_car" speedFactor="1.10" vaporized=""/>
    <tripinfo id="W_S_183" depart="1247.00" departLane="E9_1" departPos="5.10" departSpeed="10.00" departDelay="0.00" arrival="1473.00" arrivalLane="E23_0" arrivalPos="251.04" arrivalSpeed="14.59" duration="226.00" routeLength="1083.25" waitingTime="114.00" waitingCount="2" stopTime="0.00" timeLoss="152.28" rerouteNo="0" devices="tripinfo_W_S_183" vType="standard_car" speedFactor="1.08" vaporized=""/>
    <tripinfo id="N_S_192" depart="1407.00" departLane="E10_1" departPos="5.10" departSpeed="10.00" departDelay="0.00" arrival="1497.00" arrivalLane="E24_0" arrivalPos="229.28" arrivalSpeed="14.96" duration="90.00" routeLength="1051.83" waitingTime="0.00" waitingCount="0" stopTime="0.00" timeLoss="18.47" rerouteNo="0" devices="tripinfo_N_S_192" vType="standard_car" speedFactor="1.10" vaporized=""/>
    <tripinfo id="W_E_188" depart="1302.00" departLane="E9_2" departPos="5.10" departSpeed="10.00" departDelay="0.00" arrival="1509.00" arrivalLane="E22_0" arrivalPos="258.43" arrivalSpeed="13.08" duration="207.00" routeLength="1065.97" waitingTime="101.00" waitingCount="2" stopTime="0.00" timeLoss="125.55" rerouteNo="0" devices="tripinfo_W_E_188" vType="standard_car" speedFactor="0.97" vaporized=""/>
    <tripinfo id="W_E_190" depart="1378.00" departLane="E9_0" departPos="5.10" departSpeed="10.00" departDelay="0.00" arrival="1514.00" arrivalLane="E22_0" arrivalPos="258.43" arrivalSpeed="12.29" duration="136.00" routeLength="1065.97" waitingTime="29.00" waitingCount="1" stopTime="0.00" timeLoss="48.79" rerouteNo="0" devices="tripinfo_W_E_190" vType="standard_car" speedFactor="0.90" vaporized=""/>
    <tripinfo id="N_W_193" depart="1433.00" departLane="E10_1" departPos="5.10" departSpeed="10.00" departDelay="0.00" arrival="1521.00" arrivalLane="E22_0" arrivalPos="258.43" arrivalSpeed="14.74" duration="88.00" routeLength="999.87" waitingTime="1.00" waitingCount="1" stopTime="0.00" timeLoss="19.33" rerouteNo="0" devices="tripinfo_N_W_193" vType="standard_car" speedFactor="1.07" vaporized=""/>
    <tripinfo id="S_E_197" depart="1665.00" departLane="E8_2" departPos="5.10" departSpeed="10.00" departDelay="0.00" arrival="1745.00" arrivalLane="E24_0" arrivalPos="229.28" arrivalSpeed="12.11" duration="80.00" routeLength="905.97" waitingTime="0.00" waitingCount="0" stopTime="0.00" timeLoss="3.86" rerouteNo="0" devices="tripinfo_S_E_197" vType="standard_car" speedFactor="0.87" vaporized=""/>
</tripinfos>
