<routes>
                <vType accel="1.0" decel="4.5" id="standard_car" length="5.0" minGap="2.5" maxSpeed="25" sigma="0.5" />

                <route id="W_N" edges="-E0 E5 E4 E3 E10"/>
                <route id="W_E" edges="-E0 E5 E4 E20"/>
                <route id="W_S" edges="-E0 E5 E30"/>
                <route id="N_W" edges="-E1 E6 E00"/>
                <route id="N_E" edges="-E1 E6 E5 E4 E20"/>
                <route id="N_S" edges="-E1 E6 E5 E30"/>
                <route id="E_W" edges="-E2 E3 E6 E00"/>
                <route id="E_N" edges="-E2 E3 E10"/>
                <route id="E_S" edges="-E2 E3 E6 E5 E30"/>
                <route id="S_W" edges="-E3 E4 E3 E6 E00"/>
                <route id="S_N" edges="-E3 E4 E3 E10"/>
                <route id="S_E" edges="-E3 E4 E20"/>
    <vehicle id="S_N_0" type="standard_car" route="S_N" depart="46.0" departLane="random" departSpeed="10" />
    <vehicle id="N_W_1" type="standard_car" route="N_W" depart="71.0" departLane="random" departSpeed="10" />
    <vehicle id="N_E_2" type="standard_car" route="N_E" depart="72.0" departLane="random" departSpeed="10" />
    <vehicle id="W_E_3" type="standard_car" route="W_E" depart="73.0" departLane="random" departSpeed="10" />
    <vehicle id="S_W_4" type="standard_car" route="S_W" depart="77.0" departLane="random" departSpeed="10" />
    <vehicle id="W_S_5" type="standard_car" route="W_S" depart="84.0" departLane="random" departSpeed="10" />
    <vehicle id="N_S_6" type="standard_car" route="N_S" depart="86.0" departLane="random" departSpeed="10" />
    <vehicle id="N_S_7" type="standard_car" route="N_S" depart="86.0" departLane="random" departSpeed="10" />
    <vehicle id="N_S_8" type="standard_car" route="N_S" depart="91.0" departLane="random" departSpeed="10" />
    <vehicle id="E_W_9" type="standard_car" route="E_W" depart="92.0" departLane="random" departSpeed="10" />
    <vehicle id="E_W_10" type="standard_car" route="E_W" depart="93.0" departLane="random" departSpeed="10" />
    <vehicle id="N_S_11" type="standard_car" route="N_S" depart="95.0" departLane="random" departSpeed="10" />
    <vehicle id="W_E_12" type="standard_car" route="W_E" depart="95.0" departLane="random" departSpeed="10" />
    <vehicle id="E_W_13" type="standard_car" route="E_W" depart="96.0" departLane="random" departSpeed="10" />
    <vehicle id="E_W_14" type="standard_car" route="E_W" depart="105.0" departLane="random" departSpeed="10" />
    <vehicle id="N_S_15" type="standard_car" route="N_S" depart="107.0" departLane="random" departSpeed="10" />
    <vehicle id="E_W_16" type="standard_car" route="E_W" depart="120.0" departLane="random" departSpeed="10" />
    <vehicle id="N_S_17" type="standard_car" route="N_S" depart="122.0" departLane="random" departSpeed="10" />
    <vehicle id="E_N_18" type="standard_car" route="E_N" depart="123.0" departLane="random" departSpeed="10" />
    <vehicle id="S_N_19" type="standard_car" route="S_N" depart="126.0" departLane="random" departSpeed="10" />
    <vehicle id="W_E_20" type="standard_car" route="W_E" depart="133.0" departLane="random" departSpeed="10" />
    <vehicle id="W_S_21" type="standard_car" route="W_S" depart="142.0" departLane="random" departSpeed="10" />
    <vehicle id="N_S_22" type="standard_car" route="N_S" depart="145.0" departLane="random" departSpeed="10" />
    <vehicle id="W_E_23" type="standard_car" route="W_E" depart="156.0" departLane="random" departSpeed="10" />
    <vehicle id="N_S_24" type="standard_car" route="N_S" depart="158.0" departLane="random" departSpeed="10" />
    <vehicle id="N_S_25" type="standard_car" route="N_S" depart="159.0" departLane="random" departSpeed="10" />
    <vehicle id="W_S_26" type="standard_car" route="W_S" depart="161.0" departLane="random" departSpeed="10" />
    <vehicle id="W_E_27" type="standard_car" route="W_E" depart="163.0" departLane="random" departSpeed="10" />
    <vehicle id="N_S_28" type="standard_car" route="N_S" depart="163.0" departLane="random" departSpeed="10" />
    <vehicle id="S_E_29" type="standard_car" route="S_E" depart="166.0" departLane="random" departSpeed="10" />
    <vehicle id="E_W_30" type="standard_car" route="E_W" depart="170.0" departLane="random" departSpeed="10" />
    <vehicle id="S_N_31" type="standard_car" route="S_N" depart="171.0" departLane="random" departSpeed="10" />
    <vehicle id="W_E_32" type="standard_car" route="W_E" depart="172.0" departLane="random" departSpeed="10" />
    <vehicle id="N_S_33" type="standard_car" route="N_S" depart="173.0" departLane="random" departSpeed="10" />
    <vehicle id="W_E_34" type="standard_car" route="W_E" depart="176.0" departLane="random" departSpeed="10" />
    <vehicle id="S_E_35" type="standard_car" route="S_E" depart="177.0" departLane="random" departSpeed="10" />
    <vehicle id="E_W_36" type="standard_car" route="E_W" depart="178.0" departLane="random" departSpeed="10" />
    <vehicle id="S_N_37" type="standard_car" route="S_N" depart="181.0" departLane="random" departSpeed="10" />
    <vehicle id="W_E_38" type="standard_car" route="W_E" depart="181.0" departLane="random" departSpeed="10" />
    <vehicle id="W_S_39" type="standard_car" route="W_S" depart="189.0" departLane="random" departSpeed="10" />
    <vehicle id="N_S_40" type="standard_car" route="N_S" depart="192.0" departLane="random" departSpeed="10" />
    <vehicle id="W_E_41" type="standard_car" route="W_E" depart="194.0" departLane="random" departSpeed="10" />
    <vehicle id="S_E_42" type="standard_car" route="S_E" depart="197.0" departLane="random" departSpeed="10" />
    <vehicle id="W_E_43" type="standard_car" route="W_E" depart="201.0" departLane="random" departSpeed="10" />
    <vehicle id="S_N_44" type="standard_car" route="S_N" depart="204.0" departLane="random" departSpeed="10" />
    <vehicle id="E_W_45" type="standard_car" route="E_W" depart="209.0" departLane="random" departSpeed="10" />
    <vehicle id="E_S_46" type="standard_car" route="E_S" depart="212.0" departLane="random" departSpeed="10" />
    <vehicle id="N_S_47" type="standard_car" route="N_S" depart="213.0" departLane="random" departSpeed="10" />
    <vehicle id="E_W_48" type="standard_car" route="E_W" depart="214.0" departLane="random" departSpeed="10" />
    <vehicle id="E_W_49" type="standard_car" route="E_W" depart="216.0" departLane="random" departSpeed="10" />
    <vehicle id="S_N_50" type="standard_car" route="S_N" depart="217.0" departLane="random" departSpeed="10" />
    <vehicle id="E_W_51" type="standard_car" route="E_W" depart="217.0" departLane="random" departSpeed="10" />
    <vehicle id="W_E_52" type="standard_car" route="W_E" depart="219.0" departLane="random" departSpeed="10" />
    <vehicle id="S_N_53" type="standard_car" route="S_N" depart="223.0" departLane="random" departSpeed="10" />
    <vehicle id="S_N_54" type="standard_car" route="S_N" depart="228.0" departLane="random" departSpeed="10" />
    <vehicle id="N_S_55" type="standard_car" route="N_S" depart="234.0" departLane="random" departSpeed="10" />
    <vehicle id="W_E_56" type="standard_car" route="W_E" depart="236.0" departLane="random" departSpeed="10" />
    <vehicle id="S_E_57" type="standard_car" route="S_E" depart="237.0" departLane="random" departSpeed="10" />
    <vehicle id="S_N_58" type="standard_car" route="S_N" depart="237.0" departLane="random" departSpeed="10" />
    <vehicle id="N_S_59" type="standard_car" route="N_S" depart="239.0" departLane="random" departSpeed="10" />
    <vehicle id="N_S_60" type="standard_car" route="N_S" depart="242.0" departLane="random" departSpeed="10" />
    <vehicle id="S_N_61" type="standard_car" route="S_N" depart="248.0" departLane="random" departSpeed="10" />
    <vehicle id="W_E_62" type="standard_car" route="W_E" depart="248.0" departLane="random" departSpeed="10" />
    <vehicle id="E_W_63" type="standard_car" route="E_W" depart="250.0" departLane="random" departSpeed="10" />
    <vehicle id="S_N_64" type="standard_car" route="S_N" depart="250.0" departLane="random" departSpeed="10" />
    <vehicle id="W_E_65" type="standard_car" route="W_E" depart="250.0" departLane="random" departSpeed="10" />
    <vehicle id="E_N_66" type="standard_car" route="E_N" depart="251.0" departLane="random" departSpeed="10" />
    <vehicle id="E_W_67" type="standard_car" route="E_W" depart="251.0" departLane="random" departSpeed="10" />
    <vehicle id="W_E_68" type="standard_car" route="W_E" depart="251.0" departLane="random" departSpeed="10" />
    <vehicle id="W_N_69" type="standard_car" route="W_N" depart="254.0" departLane="random" departSpeed="10" />
    <vehicle id="S_N_70" type="standard_car" route="S_N" depart="256.0" departLane="random" departSpeed="10" />
    <vehicle id="W_E_71" type="standard_car" route="W_E" depart="257.0" departLane="random" departSpeed="10" />
    <vehicle id="S_N_72" type="standard_car" route="S_N" depart="262.0" departLane="random" departSpeed="10" />
    <vehicle id="E_N_73" type="standard_car" route="E_N" depart="264.0" departLane="random" departSpeed="10" />
    <vehicle id="E_W_74" type="standard_car" route="E_W" depart="266.0" departLane="random" departSpeed="10" />
    <vehicle id="W_E_75" type="standard_car" route="W_E" depart="267.0" departLane="random" departSpeed="10" />
    <vehicle id="W_E_76" type="standard_car" route="W_E" depart="268.0" departLane="random" departSpeed="10" />
    <vehicle id="N_S_77" type="standard_car" route="N_S" depart="271.0" departLane="random" departSpeed="10" />
    <vehicle id="N_S_78" type="standard_car" route="N_S" depart="277.0" departLane="random" departSpeed="10" />
    <vehicle id="N_S_79" type="standard_car" route="N_S" depart="278.0" departLane="random" departSpeed="10" />
    <vehicle id="S_N_80" type="standard_car" route="S_N" depart="279.0" departLane="random" departSpeed="10" />
    <vehicle id="E_N_81" type="standard_car" route="E_N" depart="280.0" departLane="random" departSpeed="10" />
    <vehicle id="W_N_82" type="standard_car" route="W_N" depart="281.0" departLane="random" departSpeed="10" />
    <vehicle id="E_W_83" type="standard_car" route="E_W" depart="281.0" departLane="random" departSpeed="10" />
    <vehicle id="N_W_84" type="standard_car" route="N_W" depart="283.0" departLane="random" departSpeed="10" />
    <vehicle id="N_S_85" type="standard_car" route="N_S" depart="289.0" departLane="random" departSpeed="10" />
    <vehicle id="S_N_86" type="standard_car" route="S_N" depart="289.0" departLane="random" departSpeed="10" />
    <vehicle id="E_W_87" type="standard_car" route="E_W" depart="297.0" departLane="random" departSpeed="10" />
    <vehicle id="S_N_88" type="standard_car" route="S_N" depart="298.0" departLane="random" departSpeed="10" />
    <vehicle id="S_W_89" type="standard_car" route="S_W" depart="300.0" departLane="random" departSpeed="10" />
    <vehicle id="S_W_90" type="standard_car" route="S_W" depart="300.0" departLane="random" departSpeed="10" />
    <vehicle id="S_N_91" type="standard_car" route="S_N" depart="302.0" departLane="random" departSpeed="10" />
    <vehicle id="S_N_92" type="standard_car" route="S_N" depart="302.0" departLane="random" departSpeed="10" />
    <vehicle id="S_E_93" type="standard_car" route="S_E" depart="303.0" departLane="random" departSpeed="10" />
    <vehicle id="W_N_94" type="standard_car" route="W_N" depart="303.0" departLane="random" departSpeed="10" />
    <vehicle id="S_E_95" type="standard_car" route="S_E" depart="306.0" departLane="random" departSpeed="10" />
    <vehicle id="N_S_96" type="standard_car" route="N_S" depart="312.0" departLane="random" departSpeed="10" />
    <vehicle id="E_S_97" type="standard_car" route="E_S" depart="312.0" departLane="random" departSpeed="10" />
    <vehicle id="W_E_98" type="standard_car" route="W_E" depart="315.0" departLane="random" departSpeed="10" />
    <vehicle id="S_N_99" type="standard_car" route="S_N" depart="321.0" departLane="random" departSpeed="10" />
    <vehicle id="E_W_100" type="standard_car" route="E_W" depart="323.0" departLane="random" departSpeed="10" />
    <vehicle id="W_E_101" type="standard_car" route="W_E" depart="324.0" departLane="random" departSpeed="10" />
    <vehicle id="W_E_102" type="standard_car" route="W_E" depart="324.0" departLane="random" departSpeed="10" />
    <vehicle id="S_E_103" type="standard_car" route="S_E" depart="327.0" departLane="random" departSpeed="10" />
    <vehicle id="W_E_104" type="standard_car" route="W_E" depart="328.0" departLane="random" departSpeed="10" />
    <vehicle id="S_N_105" type="standard_car" route="S_N" depart="330.0" departLane="random" departSpeed="10" />
    <vehicle id="N_E_106" type="standard_car" route="N_E" depart="333.0" departLane="random" departSpeed="10" />
    <vehicle id="E_W_107" type="standard_car" route="E_W" depart="335.0" departLane="random" departSpeed="10" />
    <vehicle id="S_N_108" type="standard_car" route="S_N" depart="336.0" departLane="random" departSpeed="10" />
    <vehicle id="W_E_109" type="standard_car" route="W_E" depart="336.0" departLane="random" departSpeed="10" />
    <vehicle id="E_W_110" type="standard_car" route="E_W" depart="339.0" departLane="random" departSpeed="10" />
    <vehicle id="E_W_111" type="standard_car" route="E_W" depart="342.0" departLane="random" departSpeed="10" />
    <vehicle id="S_N_112" type="standard_car" route="S_N" depart="343.0" departLane="random" departSpeed="10" />
    <vehicle id="S_N_113" type="standard_car" route="S_N" depart="343.0" departLane="random" departSpeed="10" />
    <vehicle id="N_S_114" type="standard_car" route="N_S" depart="343.0" departLane="random" departSpeed="10" />
    <vehicle id="S_N_115" type="standard_car" route="S_N" depart="344.0" departLane="random" departSpeed="10" />
    <vehicle id="W_S_116" type="standard_car" route="W_S" depart="347.0" departLane="random" departSpeed="10" />
    <vehicle id="S_N_117" type="standard_car" route="S_N" depart="347.0" departLane="random" departSpeed="10" />
    <vehicle id="E_W_118" type="standard_car" route="E_W" depart="347.0" departLane="random" departSpeed="10" />
    <vehicle id="S_W_119" type="standard_car" route="S_W" depart="349.0" departLane="random" departSpeed="10" />
    <vehicle id="S_N_120" type="standard_car" route="S_N" depart="350.0" departLane="random" departSpeed="10" />
    <vehicle id="N_S_121" type="standard_car" route="N_S" depart="350.0" departLane="random" departSpeed="10" />
    <vehicle id="E_W_122" type="standard_car" route="E_W" depart="353.0" departLane="random" departSpeed="10" />
    <vehicle id="E_W_123" type="standard_car" route="E_W" depart="354.0" departLane="random" departSpeed="10" />
    <vehicle id="N_S_124" type="standard_car" route="N_S" depart="354.0" departLane="random" departSpeed="10" />
    <vehicle id="S_N_125" type="standard_car" route="S_N" depart="356.0" departLane="random" departSpeed="10" />
    <vehicle id="S_N_126" type="standard_car" route="S_N" depart="357.0" departLane="random" departSpeed="10" />
    <vehicle id="N_E_127" type="standard_car" route="N_E" depart="357.0" departLane="random" departSpeed="10" />
    <vehicle id="E_W_128" type="standard_car" route="E_W" depart="359.0" departLane="random" departSpeed="10" />
    <vehicle id="E_S_129" type="standard_car" route="E_S" depart="360.0" departLane="random" departSpeed="10" />
    <vehicle id="W_E_130" type="standard_car" route="W_E" depart="360.0" departLane="random" departSpeed="10" />
    <vehicle id="W_E_131" type="standard_car" route="W_E" depart="361.0" departLane="random" departSpeed="10" />
    <vehicle id="S_N_132" type="standard_car" route="S_N" depart="361.0" departLane="random" departSpeed="10" />
    <vehicle id="E_W_133" type="standard_car" route="E_W" depart="365.0" departLane="random" departSpeed="10" />
    <vehicle id="N_S_134" type="standard_car" route="N_S" depart="365.0" departLane="random" departSpeed="10" />
    <vehicle id="W_E_135" type="standard_car" route="W_E" depart="368.0" departLane="random" departSpeed="10" />
    <vehicle id="S_N_136" type="standard_car" route="S_N" depart="369.0" departLane="random" departSpeed="10" />
    <vehicle id="S_N_137" type="standard_car" route="S_N" depart="370.0" departLane="random" departSpeed="10" />
    <vehicle id="W_E_138" type="standard_car" route="W_E" depart="370.0" departLane="random" departSpeed="10" />
    <vehicle id="S_N_139" type="standard_car" route="S_N" depart="374.0" departLane="random" departSpeed="10" />
    <vehicle id="E_W_140" type="standard_car" route="E_W" depart="374.0" departLane="random" departSpeed="10" />
    <vehicle id="E_N_141" type="standard_car" route="E_N" depart="375.0" departLane="random" departSpeed="10" />
    <vehicle id="W_E_142" type="standard_car" route="W_E" depart="376.0" departLane="random" departSpeed="10" />
    <vehicle id="N_S_143" type="standard_car" route="N_S" depart="376.0" departLane="random" departSpeed="10" />
    <vehicle id="E_W_144" type="standard_car" route="E_W" depart="377.0" departLane="random" departSpeed="10" />
    <vehicle id="S_N_145" type="standard_car" route="S_N" depart="378.0" departLane="random" departSpeed="10" />
    <vehicle id="N_W_146" type="standard_car" route="N_W" depart="380.0" departLane="random" departSpeed="10" />
    <vehicle id="W_E_147" type="standard_car" route="W_E" depart="380.0" departLane="random" departSpeed="10" />
    <vehicle id="N_S_148" type="standard_car" route="N_S" depart="383.0" departLane="random" departSpeed="10" />
    <vehicle id="W_E_149" type="standard_car" route="W_E" depart="384.0" departLane="random" departSpeed="10" />
    <vehicle id="S_E_150" type="standard_car" route="S_E" depart="385.0" departLane="random" departSpeed="10" />
    <vehicle id="E_W_151" type="standard_car" route="E_W" depart="388.0" departLane="random" departSpeed="10" />
    <vehicle id="S_W_152" type="standard_car" route="S_W" depart="389.0" departLane="random" departSpeed="10" />
    <vehicle id="W_E_153" type="standard_car" route="W_E" depart="390.0" departLane="random" departSpeed="10" />
    <vehicle id="W_E_154" type="standard_car" route="W_E" depart="390.0" departLane="random" departSpeed="10" />
    <vehicle id="W_E_155" type="standard_car" route="W_E" depart="392.0" departLane="random" departSpeed="10" />
    <vehicle id="S_N_156" type="standard_car" route="S_N" depart="392.0" departLane="random" departSpeed="10" />
    <vehicle id="S_N_157" type="standard_car" route="S_N" depart="393.0" departLane="random" departSpeed="10" />
    <vehicle id="N_S_158" type="standard_car" route="N_S" depart="395.0" departLane="random" departSpeed="10" />
    <vehicle id="S_N_159" type="standard_car" route="S_N" depart="395.0" departLane="random" departSpeed="10" />
    <vehicle id="S_N_160" type="standard_car" route="S_N" depart="396.0" departLane="random" departSpeed="10" />
    <vehicle id="W_E_161" type="standard_car" route="W_E" depart="397.0" departLane="random" departSpeed="10" />
    <vehicle id="W_E_162" type="standard_car" route="W_E" depart="399.0" departLane="random" departSpeed="10" />
    <vehicle id="N_S_163" type="standard_car" route="N_S" depart="399.0" departLane="random" departSpeed="10" />
    <vehicle id="N_E_164" type="standard_car" route="N_E" depart="402.0" departLane="random" departSpeed="10" />
    <vehicle id="E_W_165" type="standard_car" route="E_W" depart="404.0" departLane="random" departSpeed="10" />
    <vehicle id="S_N_166" type="standard_car" route="S_N" depart="408.0" departLane="random" departSpeed="10" />
    <vehicle id="N_W_167" type="standard_car" route="N_W" depart="408.0" departLane="random" departSpeed="10" />
    <vehicle id="S_E_168" type="standard_car" route="S_E" depart="410.0" departLane="random" departSpeed="10" />
    <vehicle id="S_E_169" type="standard_car" route="S_E" depart="412.0" departLane="random" departSpeed="10" />
    <vehicle id="W_S_170" type="standard_car" route="W_S" depart="413.0" departLane="random" departSpeed="10" />
    <vehicle id="W_E_171" type="standard_car" route="W_E" depart="414.0" departLane="random" departSpeed="10" />
    <vehicle id="N_S_172" type="standard_car" route="N_S" depart="419.0" departLane="random" departSpeed="10" />
    <vehicle id="S_N_173" type="standard_car" route="S_N" depart="420.0" departLane="random" departSpeed="10" />
    <vehicle id="S_N_174" type="standard_car" route="S_N" depart="424.0" departLane="random" departSpeed="10" />
    <vehicle id="W_E_175" type="standard_car" route="W_E" depart="428.0" departLane="random" departSpeed="10" />
    <vehicle id="S_E_176" type="standard_car" route="S_E" depart="434.0" departLane="random" departSpeed="10" />
    <vehicle id="S_W_177" type="standard_car" route="S_W" depart="435.0" departLane="random" departSpeed="10" />
    <vehicle id="N_S_178" type="standard_car" route="N_S" depart="436.0" departLane="random" departSpeed="10" />
    <vehicle id="W_E_179" type="standard_car" route="W_E" depart="442.0" departLane="random" departSpeed="10" />
    <vehicle id="E_W_180" type="standard_car" route="E_W" depart="442.0" departLane="random" departSpeed="10" />
    <vehicle id="W_E_181" type="standard_car" route="W_E" depart="443.0" departLane="random" departSpeed="10" />
    <vehicle id="W_E_182" type="standard_car" route="W_E" depart="445.0" departLane="random" departSpeed="10" />
    <vehicle id="E_W_183" type="standard_car" route="E_W" depart="445.0" departLane="random" departSpeed="10" />
    <vehicle id="W_E_184" type="standard_car" route="W_E" depart="446.0" departLane="random" departSpeed="10" />
    <vehicle id="N_S_185" type="standard_car" route="N_S" depart="448.0" departLane="random" departSpeed="10" />
    <vehicle id="N_W_186" type="standard_car" route="N_W" depart="451.0" departLane="random" departSpeed="10" />
    <vehicle id="S_W_187" type="standard_car" route="S_W" depart="452.0" departLane="random" departSpeed="10" />
    <vehicle id="E_S_188" type="standard_car" route="E_S" depart="452.0" departLane="random" departSpeed="10" />
    <vehicle id="S_N_189" type="standard_car" route="S_N" depart="454.0" departLane="random" departSpeed="10" />
    <vehicle id="E_W_190" type="standard_car" route="E_W" depart="456.0" departLane="random" departSpeed="10" />
    <vehicle id="S_N_191" type="standard_car" route="S_N" depart="456.0" departLane="random" departSpeed="10" />
    <vehicle id="S_N_192" type="standard_car" route="S_N" depart="456.0" departLane="random" departSpeed="10" />
    <vehicle id="W_S_193" type="standard_car" route="W_S" depart="459.0" departLane="random" departSpeed="10" />
    <vehicle id="N_S_194" type="standard_car" route="N_S" depart="460.0" departLane="random" departSpeed="10" />
    <vehicle id="S_W_195" type="standard_car" route="S_W" depart="461.0" departLane="random" departSpeed="10" />
    <vehicle id="N_E_196" type="standard_car" route="N_E" depart="463.0" departLane="random" departSpeed="10" />
    <vehicle id="W_E_197" type="standard_car" route="W_E" depart="464.0" departLane="random" departSpeed="10" />
    <vehicle id="W_E_198" type="standard_car" route="W_E" depart="464.0" departLane="random" departSpeed="10" />
    <vehicle id="W_E_199" type="standard_car" route="W_E" depart="471.0" departLane="random" departSpeed="10" />
    <vehicle id="W_E_200" type="standard_car" route="W_E" depart="473.0" departLane="random" departSpeed="10" />
    <vehicle id="S_W_201" type="standard_car" route="S_W" depart="474.0" departLane="random" departSpeed="10" />
    <vehicle id="W_E_202" type="standard_car" route="W_E" depart="475.0" departLane="random" departSpeed="10" />
    <vehicle id="E_W_203" type="standard_car" route="E_W" depart="475.0" departLane="random" departSpeed="10" />
    <vehicle id="W_S_204" type="standard_car" route="W_S" depart="476.0" departLane="random" departSpeed="10" />
    <vehicle id="S_N_205" type="standard_car" route="S_N" depart="477.0" departLane="random" departSpeed="10" />
    <vehicle id="E_N_206" type="standard_car" route="E_N" depart="478.0" departLane="random" departSpeed="10" />
    <vehicle id="W_E_207" type="standard_car" route="W_E" depart="482.0" departLane="random" departSpeed="10" />
    <vehicle id="E_W_208" type="standard_car" route="E_W" depart="482.0" departLane="random" departSpeed="10" />
    <vehicle id="E_W_209" type="standard_car" route="E_W" depart="482.0" departLane="random" departSpeed="10" />
    <vehicle id="S_N_210" type="standard_car" route="S_N" depart="484.0" departLane="random" departSpeed="10" />
    <vehicle id="S_N_211" type="standard_car" route="S_N" depart="488.0" departLane="random" departSpeed="10" />
    <vehicle id="W_E_212" type="standard_car" route="W_E" depart="488.0" departLane="random" departSpeed="10" />
    <vehicle id="W_E_213" type="standard_car" route="W_E" depart="488.0" departLane="random" departSpeed="10" />
    <vehicle id="N_S_214" type="standard_car" route="N_S" depart="490.0" departLane="random" departSpeed="10" />
    <vehicle id="E_W_215" type="standard_car" route="E_W" depart="492.0" departLane="random" departSpeed="10" />
    <vehicle id="W_E_216" type="standard_car" route="W_E" depart="495.0" departLane="random" departSpeed="10" />
    <vehicle id="S_N_217" type="standard_car" route="S_N" depart="495.0" departLane="random" departSpeed="10" />
    <vehicle id="E_N_218" type="standard_car" route="E_N" depart="495.0" departLane="random" departSpeed="10" />
    <vehicle id="S_N_219" type="standard_car" route="S_N" depart="495.0" departLane="random" departSpeed="10" />
    <vehicle id="W_E_220" type="standard_car" route="W_E" depart="496.0" departLane="random" departSpeed="10" />
    <vehicle id="E_W_221" type="standard_car" route="E_W" depart="499.0" departLane="random" departSpeed="10" />
    <vehicle id="E_W_222" type="standard_car" route="E_W" depart="499.0" departLane="random" departSpeed="10" />
    <vehicle id="S_N_223" type="standard_car" route="S_N" depart="500.0" departLane="random" departSpeed="10" />
    <vehicle id="S_W_224" type="standard_car" route="S_W" depart="501.0" departLane="random" departSpeed="10" />
    <vehicle id="S_N_225" type="standard_car" route="S_N" depart="503.0" departLane="random" departSpeed="10" />
    <vehicle id="W_E_226" type="standard_car" route="W_E" depart="504.0" departLane="random" departSpeed="10" />
    <vehicle id="W_E_227" type="standard_car" route="W_E" depart="505.0" departLane="random" departSpeed="10" />
    <vehicle id="N_S_228" type="standard_car" route="N_S" depart="506.0" departLane="random" departSpeed="10" />
    <vehicle id="S_N_229" type="standard_car" route="S_N" depart="507.0" departLane="random" departSpeed="10" />
    <vehicle id="W_S_230" type="standard_car" route="W_S" depart="513.0" departLane="random" departSpeed="10" />
    <vehicle id="N_S_231" type="standard_car" route="N_S" depart="515.0" departLane="random" departSpeed="10" />
    <vehicle id="E_W_232" type="standard_car" route="E_W" depart="517.0" departLane="random" departSpeed="10" />
    <vehicle id="W_E_233" type="standard_car" route="W_E" depart="518.0" departLane="random" departSpeed="10" />
    <vehicle id="S_N_234" type="standard_car" route="S_N" depart="518.0" departLane="random" departSpeed="10" />
    <vehicle id="N_S_235" type="standard_car" route="N_S" depart="519.0" departLane="random" departSpeed="10" />
    <vehicle id="S_W_236" type="standard_car" route="S_W" depart="520.0" departLane="random" departSpeed="10" />
    <vehicle id="S_W_237" type="standard_car" route="S_W" depart="520.0" departLane="random" departSpeed="10" />
    <vehicle id="W_E_238" type="standard_car" route="W_E" depart="520.0" departLane="random" departSpeed="10" />
    <vehicle id="S_N_239" type="standard_car" route="S_N" depart="521.0" departLane="random" departSpeed="10" />
    <vehicle id="N_E_240" type="standard_car" route="N_E" depart="521.0" departLane="random" departSpeed="10" />
    <vehicle id="S_N_241" type="standard_car" route="S_N" depart="522.0" departLane="random" departSpeed="10" />
    <vehicle id="W_E_242" type="standard_car" route="W_E" depart="522.0" departLane="random" departSpeed="10" />
    <vehicle id="S_N_243" type="standard_car" route="S_N" depart="523.0" departLane="random" departSpeed="10" />
    <vehicle id="E_W_244" type="standard_car" route="E_W" depart="524.0" departLane="random" departSpeed="10" />
    <vehicle id="E_W_245" type="standard_car" route="E_W" depart="526.0" departLane="random" departSpeed="10" />
    <vehicle id="N_S_246" type="standard_car" route="N_S" depart="528.0" departLane="random" departSpeed="10" />
    <vehicle id="W_E_247" type="standard_car" route="W_E" depart="530.0" departLane="random" departSpeed="10" />
    <vehicle id="E_W_248" type="standard_car" route="E_W" depart="538.0" departLane="random" departSpeed="10" />
    <vehicle id="N_W_249" type="standard_car" route="N_W" depart="544.0" departLane="random" departSpeed="10" />
    <vehicle id="W_E_250" type="standard_car" route="W_E" depart="546.0" departLane="random" departSpeed="10" />
    <vehicle id="N_S_251" type="standard_car" route="N_S" depart="547.0" departLane="random" departSpeed="10" />
    <vehicle id="E_S_252" type="standard_car" route="E_S" depart="547.0" departLane="random" departSpeed="10" />
    <vehicle id="S_N_253" type="standard_car" route="S_N" depart="553.0" departLane="random" departSpeed="10" />
    <vehicle id="W_E_254" type="standard_car" route="W_E" depart="556.0" departLane="random" departSpeed="10" />
    <vehicle id="N_S_255" type="standard_car" route="N_S" depart="557.0" departLane="random" departSpeed="10" />
    <vehicle id="S_W_256" type="standard_car" route="S_W" depart="560.0" departLane="random" departSpeed="10" />
    <vehicle id="N_S_257" type="standard_car" route="N_S" depart="563.0" departLane="random" departSpeed="10" />
    <vehicle id="E_W_258" type="standard_car" route="E_W" depart="564.0" departLane="random" departSpeed="10" />
    <vehicle id="W_S_259" type="standard_car" route="W_S" depart="569.0" departLane="random" departSpeed="10" />
    <vehicle id="E_W_260" type="standard_car" route="E_W" depart="569.0" departLane="random" departSpeed="10" />
    <vehicle id="S_N_261" type="standard_car" route="S_N" depart="570.0" departLane="random" departSpeed="10" />
    <vehicle id="E_W_262" type="standard_car" route="E_W" depart="570.0" departLane="random" departSpeed="10" />
    <vehicle id="N_S_263" type="standard_car" route="N_S" depart="572.0" departLane="random" departSpeed="10" />
    <vehicle id="W_S_264" type="standard_car" route="W_S" depart="573.0" departLane="random" departSpeed="10" />
    <vehicle id="N_E_265" type="standard_car" route="N_E" depart="574.0" departLane="random" departSpeed="10" />
    <vehicle id="W_E_266" type="standard_car" route="W_E" depart="578.0" departLane="random" departSpeed="10" />
    <vehicle id="W_E_267" type="standard_car" route="W_E" depart="584.0" departLane="random" departSpeed="10" />
    <vehicle id="S_N_268" type="standard_car" route="S_N" depart="584.0" departLane="random" departSpeed="10" />
    <vehicle id="N_S_269" type="standard_car" route="N_S" depart="585.0" departLane="random" departSpeed="10" />
    <vehicle id="E_S_270" type="standard_car" route="E_S" depart="591.0" departLane="random" departSpeed="10" />
    <vehicle id="S_E_271" type="standard_car" route="S_E" depart="591.0" departLane="random" departSpeed="10" />
    <vehicle id="S_N_272" type="standard_car" route="S_N" depart="593.0" departLane="random" departSpeed="10" />
    <vehicle id="S_N_273" type="standard_car" route="S_N" depart="595.0" departLane="random" departSpeed="10" />
    <vehicle id="W_E_274" type="standard_car" route="W_E" depart="597.0" departLane="random" departSpeed="10" />
    <vehicle id="S_N_275" type="standard_car" route="S_N" depart="598.0" departLane="random" departSpeed="10" />
    <vehicle id="E_S_276" type="standard_car" route="E_S" depart="600.0" departLane="random" departSpeed="10" />
    <vehicle id="E_W_277" type="standard_car" route="E_W" depart="602.0" departLane="random" departSpeed="10" />
    <vehicle id="S_N_278" type="standard_car" route="S_N" depart="609.0" departLane="random" departSpeed="10" />
    <vehicle id="W_E_279" type="standard_car" route="W_E" depart="610.0" departLane="random" departSpeed="10" />
    <vehicle id="W_E_280" type="standard_car" route="W_E" depart="611.0" departLane="random" departSpeed="10" />
    <vehicle id="S_N_281" type="standard_car" route="S_N" depart="611.0" departLane="random" departSpeed="10" />
    <vehicle id="N_W_282" type="standard_car" route="N_W" depart="612.0" departLane="random" departSpeed="10" />
    <vehicle id="N_S_283" type="standard_car" route="N_S" depart="612.0" departLane="random" departSpeed="10" />
    <vehicle id="N_S_284" type="standard_car" route="N_S" depart="613.0" departLane="random" departSpeed="10" />
    <vehicle id="E_N_285" type="standard_car" route="E_N" depart="614.0" departLane="random" departSpeed="10" />
    <vehicle id="W_E_286" type="standard_car" route="W_E" depart="616.0" departLane="random" departSpeed="10" />
    <vehicle id="S_N_287" type="standard_car" route="S_N" depart="617.0" departLane="random" departSpeed="10" />
    <vehicle id="E_W_288" type="standard_car" route="E_W" depart="617.0" departLane="random" departSpeed="10" />
    <vehicle id="S_N_289" type="standard_car" route="S_N" depart="618.0" departLane="random" departSpeed="10" />
    <vehicle id="W_N_290" type="standard_car" route="W_N" depart="619.0" departLane="random" departSpeed="10" />
    <vehicle id="E_S_291" type="standard_car" route="E_S" depart="619.0" departLane="random" departSpeed="10" />
    <vehicle id="E_W_292" type="standard_car" route="E_W" depart="622.0" departLane="random" departSpeed="10" />
    <vehicle id="W_E_293" type="standard_car" route="W_E" depart="625.0" departLane="random" departSpeed="10" />
    <vehicle id="W_E_294" type="standard_car" route="W_E" depart="626.0" departLane="random" departSpeed="10" />
    <vehicle id="W_E_295" type="standard_car" route="W_E" depart="626.0" departLane="random" departSpeed="10" />
    <vehicle id="N_S_296" type="standard_car" route="N_S" depart="627.0" departLane="random" departSpeed="10" />
    <vehicle id="S_N_297" type="standard_car" route="S_N" depart="627.0" departLane="random" departSpeed="10" />
    <vehicle id="E_W_298" type="standard_car" route="E_W" depart="628.0" departLane="random" departSpeed="10" />
    <vehicle id="W_S_299" type="standard_car" route="W_S" depart="629.0" departLane="random" departSpeed="10" />
    <vehicle id="E_W_300" type="standard_car" route="E_W" depart="630.0" departLane="random" departSpeed="10" />
    <vehicle id="E_N_301" type="standard_car" route="E_N" depart="630.0" departLane="random" departSpeed="10" />
    <vehicle id="W_E_302" type="standard_car" route="W_E" depart="631.0" departLane="random" departSpeed="10" />
    <vehicle id="N_S_303" type="standard_car" route="N_S" depart="631.0" departLane="random" departSpeed="10" />
    <vehicle id="W_E_304" type="standard_car" route="W_E" depart="641.0" departLane="random" departSpeed="10" />
    <vehicle id="W_S_305" type="standard_car" route="W_S" depart="642.0" departLane="random" departSpeed="10" />
    <vehicle id="W_N_306" type="standard_car" route="W_N" depart="642.0" departLane="random" departSpeed="10" />
    <vehicle id="W_E_307" type="standard_car" route="W_E" depart="644.0" departLane="random" departSpeed="10" />
    <vehicle id="W_E_308" type="standard_car" route="W_E" depart="649.0" departLane="random" departSpeed="10" />
    <vehicle id="E_S_309" type="standard_car" route="E_S" depart="650.0" departLane="random" departSpeed="10" />
    <vehicle id="N_S_310" type="standard_car" route="N_S" depart="651.0" departLane="random" departSpeed="10" />
    <vehicle id="S_N_311" type="standard_car" route="S_N" depart="652.0" departLane="random" departSpeed="10" />
    <vehicle id="S_N_312" type="standard_car" route="S_N" depart="653.0" departLane="random" departSpeed="10" />
    <vehicle id="S_E_313" type="standard_car" route="S_E" depart="654.0" departLane="random" departSpeed="10" />
    <vehicle id="N_S_314" type="standard_car" route="N_S" depart="654.0" departLane="random" departSpeed="10" />
    <vehicle id="E_W_315" type="standard_car" route="E_W" depart="654.0" departLane="random" departSpeed="10" />
    <vehicle id="E_S_316" type="standard_car" route="E_S" depart="654.0" departLane="random" departSpeed="10" />
    <vehicle id="N_S_317" type="standard_car" route="N_S" depart="657.0" departLane="random" departSpeed="10" />
    <vehicle id="S_N_318" type="standard_car" route="S_N" depart="664.0" departLane="random" departSpeed="10" />
    <vehicle id="S_E_319" type="standard_car" route="S_E" depart="664.0" departLane="random" departSpeed="10" />
    <vehicle id="N_E_320" type="standard_car" route="N_E" depart="665.0" departLane="random" departSpeed="10" />
    <vehicle id="E_W_321" type="standard_car" route="E_W" depart="668.0" departLane="random" departSpeed="10" />
    <vehicle id="S_N_322" type="standard_car" route="S_N" depart="670.0" departLane="random" departSpeed="10" />
    <vehicle id="E_W_323" type="standard_car" route="E_W" depart="673.0" departLane="random" departSpeed="10" />
    <vehicle id="E_S_324" type="standard_car" route="E_S" depart="673.0" departLane="random" departSpeed="10" />
    <vehicle id="E_W_325" type="standard_car" route="E_W" depart="674.0" departLane="random" departSpeed="10" />
    <vehicle id="S_W_326" type="standard_car" route="S_W" depart="678.0" departLane="random" departSpeed="10" />
    <vehicle id="N_S_327" type="standard_car" route="N_S" depart="679.0" departLane="random" departSpeed="10" />
    <vehicle id="W_E_328" type="standard_car" route="W_E" depart="679.0" departLane="random" departSpeed="10" />
    <vehicle id="S_N_329" type="standard_car" route="S_N" depart="685.0" departLane="random" departSpeed="10" />
    <vehicle id="E_W_330" type="standard_car" route="E_W" depart="686.0" departLane="random" departSpeed="10" />
    <vehicle id="E_W_331" type="standard_car" route="E_W" depart="686.0" departLane="random" departSpeed="10" />
    <vehicle id="E_W_332" type="standard_car" route="E_W" depart="689.0" departLane="random" departSpeed="10" />
    <vehicle id="E_S_333" type="standard_car" route="E_S" depart="693.0" departLane="random" departSpeed="10" />
    <vehicle id="N_S_334" type="standard_car" route="N_S" depart="695.0" departLane="random" departSpeed="10" />
    <vehicle id="E_N_335" type="standard_car" route="E_N" depart="695.0" departLane="random" departSpeed="10" />
    <vehicle id="N_S_336" type="standard_car" route="N_S" depart="698.0" departLane="random" departSpeed="10" />
    <vehicle id="E_W_337" type="standard_car" route="E_W" depart="699.0" departLane="random" departSpeed="10" />
    <vehicle id="S_N_338" type="standard_car" route="S_N" depart="699.0" departLane="random" departSpeed="10" />
    <vehicle id="N_S_339" type="standard_car" route="N_S" depart="702.0" departLane="random" departSpeed="10" />
    <vehicle id="W_E_340" type="standard_car" route="W_E" depart="703.0" departLane="random" departSpeed="10" />
    <vehicle id="W_S_341" type="standard_car" route="W_S" depart="704.0" departLane="random" departSpeed="10" />
    <vehicle id="E_W_342" type="standard_car" route="E_W" depart="710.0" departLane="random" departSpeed="10" />
    <vehicle id="E_W_343" type="standard_car" route="E_W" depart="711.0" departLane="random" departSpeed="10" />
    <vehicle id="S_N_344" type="standard_car" route="S_N" depart="713.0" departLane="random" departSpeed="10" />
    <vehicle id="E_S_345" type="standard_car" route="E_S" depart="713.0" departLane="random" departSpeed="10" />
    <vehicle id="E_S_346" type="standard_car" route="E_S" depart="715.0" departLane="random" departSpeed="10" />
    <vehicle id="S_N_347" type="standard_car" route="S_N" depart="719.0" departLane="random" departSpeed="10" />
    <vehicle id="E_W_348" type="standard_car" route="E_W" depart="721.0" departLane="random" departSpeed="10" />
    <vehicle id="E_W_349" type="standard_car" route="E_W" depart="721.0" departLane="random" departSpeed="10" />
    <vehicle id="W_N_350" type="standard_car" route="W_N" depart="724.0" departLane="random" departSpeed="10" />
    <vehicle id="W_N_351" type="standard_car" route="W_N" depart="724.0" departLane="random" departSpeed="10" />
    <vehicle id="S_E_352" type="standard_car" route="S_E" depart="727.0" departLane="random" departSpeed="10" />
    <vehicle id="W_E_353" type="standard_car" route="W_E" depart="728.0" departLane="random" departSpeed="10" />
    <vehicle id="W_E_354" type="standard_car" route="W_E" depart="728.0" departLane="random" departSpeed="10" />
    <vehicle id="S_N_355" type="standard_car" route="S_N" depart="729.0" departLane="random" departSpeed="10" />
    <vehicle id="W_E_356" type="standard_car" route="W_E" depart="729.0" departLane="random" departSpeed="10" />
    <vehicle id="N_S_357" type="standard_car" route="N_S" depart="731.0" departLane="random" departSpeed="10" />
    <vehicle id="W_E_358" type="standard_car" route="W_E" depart="731.0" departLane="random" departSpeed="10" />
    <vehicle id="N_W_359" type="standard_car" route="N_W" depart="731.0" departLane="random" departSpeed="10" />
    <vehicle id="S_N_360" type="standard_car" route="S_N" depart="735.0" departLane="random" departSpeed="10" />
    <vehicle id="N_S_361" type="standard_car" route="N_S" depart="736.0" departLane="random" departSpeed="10" />
    <vehicle id="W_E_362" type="standard_car" route="W_E" depart="738.0" departLane="random" departSpeed="10" />
    <vehicle id="S_N_363" type="standard_car" route="S_N" depart="746.0" departLane="random" departSpeed="10" />
    <vehicle id="N_S_364" type="standard_car" route="N_S" depart="747.0" departLane="random" departSpeed="10" />
    <vehicle id="E_W_365" type="standard_car" route="E_W" depart="748.0" departLane="random" departSpeed="10" />
    <vehicle id="E_N_366" type="standard_car" route="E_N" depart="749.0" departLane="random" departSpeed="10" />
    <vehicle id="S_N_367" type="standard_car" route="S_N" depart="754.0" departLane="random" departSpeed="10" />
    <vehicle id="E_W_368" type="standard_car" route="E_W" depart="757.0" departLane="random" departSpeed="10" />
    <vehicle id="W_E_369" type="standard_car" route="W_E" depart="758.0" departLane="random" departSpeed="10" />
    <vehicle id="S_N_370" type="standard_car" route="S_N" depart="758.0" departLane="random" departSpeed="10" />
    <vehicle id="N_W_371" type="standard_car" route="N_W" depart="760.0" departLane="random" departSpeed="10" />
    <vehicle id="E_W_372" type="standard_car" route="E_W" depart="763.0" departLane="random" departSpeed="10" />
    <vehicle id="N_S_373" type="standard_car" route="N_S" depart="763.0" departLane="random" departSpeed="10" />
    <vehicle id="S_N_374" type="standard_car" route="S_N" depart="764.0" departLane="random" departSpeed="10" />
    <vehicle id="S_N_375" type="standard_car" route="S_N" depart="764.0" departLane="random" departSpeed="10" />
    <vehicle id="W_E_376" type="standard_car" route="W_E" depart="768.0" departLane="random" departSpeed="10" />
    <vehicle id="W_E_377" type="standard_car" route="W_E" depart="773.0" departLane="random" departSpeed="10" />
    <vehicle id="N_E_378" type="standard_car" route="N_E" depart="773.0" departLane="random" departSpeed="10" />
    <vehicle id="W_E_379" type="standard_car" route="W_E" depart="783.0" departLane="random" departSpeed="10" />
    <vehicle id="W_E_380" type="standard_car" route="W_E" depart="784.0" departLane="random" departSpeed="10" />
    <vehicle id="N_S_381" type="standard_car" route="N_S" depart="786.0" departLane="random" departSpeed="10" />
    <vehicle id="E_W_382" type="standard_car" route="E_W" depart="793.0" departLane="random" departSpeed="10" />
    <vehicle id="N_S_383" type="standard_car" route="N_S" depart="795.0" departLane="random" departSpeed="10" />
    <vehicle id="W_E_384" type="standard_car" route="W_E" depart="803.0" departLane="random" departSpeed="10" />
    <vehicle id="E_W_385" type="standard_car" route="E_W" depart="809.0" departLane="random" departSpeed="10" />
    <vehicle id="E_W_386" type="standard_car" route="E_W" depart="813.0" departLane="random" departSpeed="10" />
    <vehicle id="S_N_387" type="standard_car" route="S_N" depart="813.0" departLane="random" departSpeed="10" />
    <vehicle id="S_N_388" type="standard_car" route="S_N" depart="817.0" departLane="random" departSpeed="10" />
    <vehicle id="E_S_389" type="standard_car" route="E_S" depart="818.0" departLane="random" departSpeed="10" />
    <vehicle id="E_W_390" type="standard_car" route="E_W" depart="819.0" departLane="random" departSpeed="10" />
    <vehicle id="S_N_391" type="standard_car" route="S_N" depart="821.0" departLane="random" departSpeed="10" />
    <vehicle id="S_W_392" type="standard_car" route="S_W" depart="824.0" departLane="random" departSpeed="10" />
    <vehicle id="N_S_393" type="standard_car" route="N_S" depart="827.0" departLane="random" departSpeed="10" />
    <vehicle id="S_N_394" type="standard_car" route="S_N" depart="831.0" departLane="random" departSpeed="10" />
    <vehicle id="W_E_395" type="standard_car" route="W_E" depart="835.0" departLane="random" departSpeed="10" />
    <vehicle id="S_N_396" type="standard_car" route="S_N" depart="838.0" departLane="random" departSpeed="10" />
    <vehicle id="W_E_397" type="standard_car" route="W_E" depart="841.0" departLane="random" departSpeed="10" />
    <vehicle id="N_E_398" type="standard_car" route="N_E" depart="843.0" departLane="random" departSpeed="10" />
    <vehicle id="E_W_399" type="standard_car" route="E_W" depart="845.0" departLane="random" departSpeed="10" />
    <vehicle id="E_W_400" type="standard_car" route="E_W" depart="845.0" departLane="random" departSpeed="10" />
    <vehicle id="N_W_401" type="standard_car" route="N_W" depart="845.0" departLane="random" departSpeed="10" />
    <vehicle id="W_S_402" type="standard_car" route="W_S" depart="854.0" departLane="random" departSpeed="10" />
    <vehicle id="S_W_403" type="standard_car" route="S_W" depart="855.0" departLane="random" departSpeed="10" />
    <vehicle id="W_E_404" type="standard_car" route="W_E" depart="864.0" departLane="random" departSpeed="10" />
    <vehicle id="N_S_405" type="standard_car" route="N_S" depart="866.0" departLane="random" departSpeed="10" />
    <vehicle id="S_N_406" type="standard_car" route="S_N" depart="867.0" departLane="random" departSpeed="10" />
    <vehicle id="W_S_407" type="standard_car" route="W_S" depart="874.0" departLane="random" departSpeed="10" />
    <vehicle id="W_E_408" type="standard_car" route="W_E" depart="874.0" departLane="random" departSpeed="10" />
    <vehicle id="N_S_409" type="standard_car" route="N_S" depart="876.0" departLane="random" departSpeed="10" />
    <vehicle id="W_E_410" type="standard_car" route="W_E" depart="885.0" departLane="random" departSpeed="10" />
    <vehicle id="N_W_411" type="standard_car" route="N_W" depart="886.0" departLane="random" departSpeed="10" />
    <vehicle id="W_S_412" type="standard_car" route="W_S" depart="889.0" departLane="random" departSpeed="10" />
    <vehicle id="E_W_413" type="standard_car" route="E_W" depart="891.0" departLane="random" departSpeed="10" />
    <vehicle id="W_S_414" type="standard_car" route="W_S" depart="899.0" departLane="random" departSpeed="10" />
    <vehicle id="E_W_415" type="standard_car" route="E_W" depart="901.0" departLane="random" departSpeed="10" />
    <vehicle id="S_N_416" type="standard_car" route="S_N" depart="912.0" departLane="random" departSpeed="10" />
    <vehicle id="E_W_417" type="standard_car" route="E_W" depart="915.0" departLane="random" departSpeed="10" />
    <vehicle id="W_E_418" type="standard_car" route="W_E" depart="917.0" departLane="random" departSpeed="10" />
    <vehicle id="S_N_419" type="standard_car" route="S_N" depart="917.0" departLane="random" departSpeed="10" />
    <vehicle id="E_W_420" type="standard_car" route="E_W" depart="928.0" departLane="random" departSpeed="10" />
    <vehicle id="E_W_421" type="standard_car" route="E_W" depart="931.0" departLane="random" departSpeed="10" />
    <vehicle id="E_W_422" type="standard_car" route="E_W" depart="936.0" departLane="random" departSpeed="10" />
    <vehicle id="N_S_423" type="standard_car" route="N_S" depart="939.0" departLane="random" departSpeed="10" />
    <vehicle id="S_W_424" type="standard_car" route="S_W" depart="941.0" departLane="random" departSpeed="10" />
    <vehicle id="N_S_425" type="standard_car" route="N_S" depart="946.0" departLane="random" departSpeed="10" />
    <vehicle id="S_E_426" type="standard_car" route="S_E" depart="947.0" departLane="random" departSpeed="10" />
    <vehicle id="N_W_427" type="standard_car" route="N_W" depart="949.0" departLane="random" departSpeed="10" />
    <vehicle id="S_N_428" type="standard_car" route="S_N" depart="951.0" departLane="random" departSpeed="10" />
    <vehicle id="S_N_429" type="standard_car" route="S_N" depart="952.0" departLane="random" departSpeed="10" />
    <vehicle id="E_W_430" type="standard_car" route="E_W" depart="957.0" departLane="random" departSpeed="10" />
    <vehicle id="W_E_431" type="standard_car" route="W_E" depart="960.0" departLane="random" departSpeed="10" />
    <vehicle id="N_S_432" type="standard_car" route="N_S" depart="964.0" departLane="random" departSpeed="10" />
    <vehicle id="E_N_433" type="standard_car" route="E_N" depart="973.0" departLane="random" departSpeed="10" />
    <vehicle id="N_S_434" type="standard_car" route="N_S" depart="974.0" departLane="random" departSpeed="10" />
    <vehicle id="W_E_435" type="standard_car" route="W_E" depart="974.0" departLane="random" departSpeed="10" />
    <vehicle id="S_E_436" type="standard_car" route="S_E" depart="975.0" departLane="random" departSpeed="10" />
    <vehicle id="W_S_437" type="standard_car" route="W_S" depart="994.0" departLane="random" departSpeed="10" />
    <vehicle id="W_S_438" type="standard_car" route="W_S" depart="994.0" departLane="random" departSpeed="10" />
    <vehicle id="E_W_439" type="standard_car" route="E_W" depart="1002.0" departLane="random" departSpeed="10" />
    <vehicle id="E_S_440" type="standard_car" route="E_S" depart="1004.0" departLane="random" departSpeed="10" />
    <vehicle id="S_N_441" type="standard_car" route="S_N" depart="1004.0" departLane="random" departSpeed="10" />
    <vehicle id="W_N_442" type="standard_car" route="W_N" depart="1005.0" departLane="random" departSpeed="10" />
    <vehicle id="S_N_443" type="standard_car" route="S_N" depart="1020.0" departLane="random" departSpeed="10" />
    <vehicle id="N_S_444" type="standard_car" route="N_S" depart="1021.0" departLane="random" departSpeed="10" />
    <vehicle id="N_W_445" type="standard_car" route="N_W" depart="1021.0" departLane="random" departSpeed="10" />
    <vehicle id="S_E_446" type="standard_car" route="S_E" depart="1023.0" departLane="random" departSpeed="10" />
    <vehicle id="E_W_447" type="standard_car" route="E_W" depart="1026.0" departLane="random" departSpeed="10" />
    <vehicle id="E_W_448" type="standard_car" route="E_W" depart="1032.0" departLane="random" departSpeed="10" />
    <vehicle id="S_N_449" type="standard_car" route="S_N" depart="1058.0" departLane="random" departSpeed="10" />
    <vehicle id="N_S_450" type="standard_car" route="N_S" depart="1073.0" departLane="random" departSpeed="10" />
    <vehicle id="W_E_451" type="standard_car" route="W_E" depart="1075.0" departLane="random" departSpeed="10" />
    <vehicle id="W_S_452" type="standard_car" route="W_S" depart="1082.0" departLane="random" departSpeed="10" />
    <vehicle id="N_S_453" type="standard_car" route="N_S" depart="1085.0" departLane="random" departSpeed="10" />
    <vehicle id="E_S_454" type="standard_car" route="E_S" depart="1085.0" departLane="random" departSpeed="10" />
    <vehicle id="W_N_455" type="standard_car" route="W_N" depart="1086.0" departLane="random" departSpeed="10" />
    <vehicle id="S_N_456" type="standard_car" route="S_N" depart="1100.0" departLane="random" departSpeed="10" />
    <vehicle id="W_N_457" type="standard_car" route="W_N" depart="1119.0" departLane="random" departSpeed="10" />
    <vehicle id="N_S_458" type="standard_car" route="N_S" depart="1120.0" departLane="random" departSpeed="10" />
    <vehicle id="E_W_459" type="standard_car" route="E_W" depart="1123.0" departLane="random" departSpeed="10" />
    <vehicle id="E_N_460" type="standard_car" route="E_N" depart="1127.0" departLane="random" departSpeed="10" />
    <vehicle id="W_E_461" type="standard_car" route="W_E" depart="1131.0" departLane="random" departSpeed="10" />
    <vehicle id="W_E_462" type="standard_car" route="W_E" depart="1133.0" departLane="random" departSpeed="10" />
    <vehicle id="S_N_463" type="standard_car" route="S_N" depart="1134.0" departLane="random" departSpeed="10" />
    <vehicle id="W_E_464" type="standard_car" route="W_E" depart="1136.0" departLane="random" departSpeed="10" />
    <vehicle id="W_N_465" type="standard_car" route="W_N" depart="1144.0" departLane="random" departSpeed="10" />
    <vehicle id="S_N_466" type="standard_car" route="S_N" depart="1151.0" departLane="random" departSpeed="10" />
    <vehicle id="E_S_467" type="standard_car" route="E_S" depart="1158.0" departLane="random" departSpeed="10" />
    <vehicle id="E_N_468" type="standard_car" route="E_N" depart="1161.0" departLane="random" departSpeed="10" />
    <vehicle id="N_S_469" type="standard_car" route="N_S" depart="1165.0" departLane="random" departSpeed="10" />
    <vehicle id="S_N_470" type="standard_car" route="S_N" depart="1165.0" departLane="random" departSpeed="10" />
    <vehicle id="N_S_471" type="standard_car" route="N_S" depart="1179.0" departLane="random" departSpeed="10" />
    <vehicle id="E_W_472" type="standard_car" route="E_W" depart="1180.0" departLane="random" departSpeed="10" />
    <vehicle id="N_S_473" type="standard_car" route="N_S" depart="1191.0" departLane="random" departSpeed="10" />
    <vehicle id="E_S_474" type="standard_car" route="E_S" depart="1192.0" departLane="random" departSpeed="10" />
    <vehicle id="W_E_475" type="standard_car" route="W_E" depart="1193.0" departLane="random" departSpeed="10" />
    <vehicle id="N_S_476" type="standard_car" route="N_S" depart="1200.0" departLane="random" departSpeed="10" />
    <vehicle id="S_N_477" type="standard_car" route="S_N" depart="1203.0" departLane="random" departSpeed="10" />
    <vehicle id="N_S_478" type="standard_car" route="N_S" depart="1205.0" departLane="random" departSpeed="10" />
    <vehicle id="E_W_479" type="standard_car" route="E_W" depart="1206.0" departLane="random" departSpeed="10" />
    <vehicle id="W_N_480" type="standard_car" route="W_N" depart="1214.0" departLane="random" departSpeed="10" />
    <vehicle id="E_W_481" type="standard_car" route="E_W" depart="1236.0" departLane="random" departSpeed="10" />
    <vehicle id="W_E_482" type="standard_car" route="W_E" depart="1237.0" departLane="random" departSpeed="10" />
    <vehicle id="W_N_483" type="standard_car" route="W_N" depart="1242.0" departLane="random" departSpeed="10" />
    <vehicle id="E_W_484" type="standard_car" route="E_W" depart="1266.0" departLane="random" departSpeed="10" />
    <vehicle id="N_S_485" type="standard_car" route="N_S" depart="1275.0" departLane="random" departSpeed="10" />
    <vehicle id="E_W_486" type="standard_car" route="E_W" depart="1284.0" departLane="random" departSpeed="10" />
    <vehicle id="N_E_487" type="standard_car" route="N_E" depart="1291.0" departLane="random" departSpeed="10" />
    <vehicle id="W_E_488" type="standard_car" route="W_E" depart="1293.0" departLane="random" departSpeed="10" />
    <vehicle id="W_E_489" type="standard_car" route="W_E" depart="1299.0" departLane="random" departSpeed="10" />
    <vehicle id="E_W_490" type="standard_car" route="E_W" depart="1307.0" departLane="random" departSpeed="10" />
    <vehicle id="S_N_491" type="standard_car" route="S_N" depart="1335.0" departLane="random" departSpeed="10" />
    <vehicle id="N_S_492" type="standard_car" route="N_S" depart="1372.0" departLane="random" departSpeed="10" />
    <vehicle id="N_S_493" type="standard_car" route="N_S" depart="1407.0" departLane="random" departSpeed="10" />
    <vehicle id="E_W_494" type="standard_car" route="E_W" depart="1422.0" departLane="random" departSpeed="10" />
    <vehicle id="E_W_495" type="standard_car" route="E_W" depart="1436.0" departLane="random" departSpeed="10" />
    <vehicle id="E_S_496" type="standard_car" route="E_S" depart="1436.0" departLane="random" departSpeed="10" />
    <vehicle id="S_N_497" type="standard_car" route="S_N" depart="1465.0" departLane="random" departSpeed="10" />
    <vehicle id="S_N_498" type="standard_car" route="S_N" depart="1518.0" departLane="random" departSpeed="10" />
    <vehicle id="N_S_499" type="standard_car" route="N_S" depart="1734.0" departLane="random" departSpeed="10" />
</routes>
